{"type": "Feature", "id": 23283352, "geometry": {"type": "Point", "coordinates": [0.14078, 40.09465]}, "properties": {"woe:id": 23283352, "woe:parent_id": 768929, "woe:name": "Estaci\u00f3n de Oropesa", "woe:placetype": 20, "woe:placetype_name": "POI", "woe:lang": "SPA", "iso:country": "ES", "meta:provider": ["geoplanet:7.3.1", "geoplanet:7.3.2", "geoplanet:7.4.0", "geoplanet:7.4.1", "geoplanet:7.5.1", "geoplanet:7.5.2", "geoplanet:7.6.0", "geoplanet:7.8.1", "geoplanet:7.9.0", "geoplanet:7.10.0", "geoplanet:8.0.0", "woeplanet:8.0.0"], "meta:indexed": "2020-08-20T20:56:19.576356", "meta:updated": "2020-10-14T11:28:16.209289", "woe:alias_SPA_S": ["Estacion de Oropesa", "Estacion del Oropesa", "Estacion Oropesa"], "woe:alias_SPA_V": ["Estaci\u00f3n Oropesa", "Estaci\u00f3n del Oropesa"], "woe:hierarchy": {"continent": 24865675, "country": 23424950, "town": 0, "planet": 1, "county": 12602138, "suburb": 0, "state": 12578038, "region": 0, "localadmin": 12695484}, "woe:timezone_id": 56043644, "woe:hash": "sp0h55n822mp", "woe:centroid": [0.14078, 40.09465], "geom:latitude": 40.09465, "geom:longitude": 0.14078, "geom:hash": "sp0h55n822mp", "woe:latitude": 40.09465, "geom:centroid": [0.14078, 40.09465], "woe:longitude": 0.14078, "woe:repo": "woeplanet-poi-es", "geom:area": 0.0, "woe:scale": 19}}