{"type": "Feature", "id": 23259403, "properties": {"woe:id": 23259403, "woe:parent_id": 20220089, "woe:name": "Estaci\u00f3n de Proven\u00e7a", "woe:placetype": 20, "woe:placetype_name": "POI", "woe:lang": "UNK", "iso:country": "ES", "meta:provider": ["geoplanet:7.3.1", "geoplanet:7.3.2", "geoplanet:7.4.0", "geoplanet:7.4.1", "geoplanet:7.5.1", "geoplanet:7.5.2", "geoplanet:7.6.0", "geoplanet:7.8.1", "geoplanet:7.9.0", "geoplanet:7.10.0", "geoplanet:8.0.0", "woeplanet:8.0.0"], "meta:indexed": "2020-08-20T20:56:19.104734", "woe:alias_UNK_V": ["Estaci\u00f3n Proven\u00e7a", "Estaci\u00f3n del Proven\u00e7a"], "woe:alias_UNK_S": ["Estacion de Provenca", "Estacion del Provenca", "Estacion Provenca"], "meta:updated": "2020-08-22T03:00:15.146574", "woe:hierarchy": {"continent": 24865675, "country": 23424950, "town": 0, "planet": 1, "county": 12602124, "suburb": 0, "state": 12578034, "region": 0, "localadmin": 12693396}, "woe:timezone_id": 56043644, "woe:hash": "sp3e3p7c83yg", "woe:centroid": [2.15849, 41.392632], "geom:latitude": 41.392632, "geom:longitude": 2.15849, "geom:hash": "sp3e3p7c83yg", "woe:latitude": 41.392632, "geom:centroid": [2.15849, 41.392632], "woe:longitude": 2.15849, "woe:repo": "woeplanet-poi-es"}, "geometry": {"coordinates": [2.15849, 41.392632], "type": "Point"}}