{"type": "Feature", "id": 23306620, "geometry": {"type": "Point", "coordinates": [-3.7129, 40.446129]}, "properties": {"woe:id": 23306620, "woe:parent_id": 20219860, "woe:name": "Estaci\u00f3n de Guzm\u00e1n El Bueno", "woe:placetype": 20, "woe:placetype_name": "POI", "woe:lang": "SPA", "iso:country": "ES", "meta:provider": ["geoplanet:7.3.1", "geoplanet:7.3.2", "geoplanet:7.4.0", "geoplanet:7.4.1", "geoplanet:7.5.1", "geoplanet:7.5.2", "geoplanet:7.6.0", "geoplanet:7.8.1", "geoplanet:7.9.0", "geoplanet:7.10.0", "geoplanet:8.0.0", "woeplanet:8.0.0"], "meta:indexed": "2020-08-20T20:56:19.930776", "meta:updated": "2020-10-14T11:28:16.387904", "woe:alias_SPA_S": ["Estacion de Guzman El Bueno", "Estacion del Guzman El Bueno", "Estacion Guzman El Bueno"], "woe:alias_SPA_V": ["Metro-Guzman El Bueno", "Metro-Guzm\u00e1n El Bueno", "Estaci\u00f3n Guzm\u00e1n El Bueno", "Estaci\u00f3n del Guzm\u00e1n El Bueno"], "woe:hierarchy": {"continent": 24865675, "country": 23424950, "town": 0, "planet": 1, "county": 12602090, "suburb": 0, "state": 12578024, "region": 0, "localadmin": 12688024}, "woe:timezone_id": 56043644, "woe:hash": "ezjq5dbrg0vj", "woe:centroid": [-3.7129, 40.446129], "geom:latitude": 40.446129, "geom:longitude": -3.7129, "geom:hash": "ezjq5dbrg0vj", "woe:latitude": 40.446129, "geom:centroid": [-3.7129, 40.446129], "woe:longitude": -3.7129, "woe:repo": "woeplanet-poi-es", "geom:area": 0.0, "woe:scale": 19}}