{"type": "Feature", "id": 23263853, "properties": {"woe:id": 23263853, "woe:parent_id": 767393, "woe:name": "Estaci\u00f3n de Mollet del Vall\u00e8s", "woe:placetype": 20, "woe:placetype_name": "POI", "woe:lang": "UNK", "iso:country": "ES", "meta:provider": ["geoplanet:7.3.1", "geoplanet:7.3.2", "geoplanet:7.4.0", "geoplanet:7.4.1", "geoplanet:7.5.1", "geoplanet:7.5.2", "geoplanet:7.6.0", "geoplanet:7.8.1", "geoplanet:7.9.0", "geoplanet:7.10.0", "geoplanet:8.0.0", "woeplanet:8.0.0"], "meta:indexed": "2020-08-20T20:56:19.240446", "woe:alias_UNK_V": ["Estaci\u00f3n Mollet del Vall\u00e8s", "Estaci\u00f3n del Mollet del Vall\u00e8s"], "woe:alias_UNK_S": ["Estacion de Mollet del Valles", "Estacion del Mollet del Valles", "Estacion Mollet del Valles"], "meta:updated": "2020-08-22T03:00:15.186324", "woe:hierarchy": {"continent": 24865675, "country": 23424950, "town": 0, "planet": 1, "county": 12602124, "suburb": 0, "state": 12578034, "region": 0, "localadmin": 12693506}, "woe:timezone_id": 56043644, "woe:hash": "sp3s61qqvu7k", "woe:centroid": [2.2061, 41.536369], "geom:latitude": 41.536369, "geom:longitude": 2.2061, "geom:hash": "sp3s61qqvu7k", "woe:latitude": 41.536369, "geom:centroid": [2.2061, 41.536369], "woe:longitude": 2.2061, "woe:repo": "woeplanet-poi-es"}, "geometry": {"coordinates": [2.2061, 41.536369], "type": "Point"}}