{"type": "Feature", "id": 23256710, "geometry": {"type": "Point", "coordinates": [2.125, 41.398682]}, "properties": {"woe:id": 23256710, "woe:parent_id": 774201, "woe:name": "Estaci\u00f3n de Sarri\u00e1", "woe:placetype": 20, "woe:placetype_name": "POI", "woe:lang": "UNK", "iso:country": "ES", "meta:provider": ["geoplanet:7.3.1", "geoplanet:7.3.2", "geoplanet:7.4.0", "geoplanet:7.4.1", "geoplanet:7.5.1", "geoplanet:7.5.2", "geoplanet:7.6.0", "geoplanet:7.8.1", "geoplanet:7.9.0", "geoplanet:7.10.0", "geoplanet:8.0.0", "woeplanet:8.0.0"], "meta:indexed": "2020-08-20T20:56:19.055358", "woe:alias_UNK_V": ["Estaci\u00f3n Sarri\u00e1", "Estaci\u00f3n del Sarri\u00e1"], "woe:alias_UNK_S": ["Estacion de Sarria", "Estacion del Sarria", "Estacion Sarria"], "meta:updated": "2020-10-14T11:28:15.589983", "woe:hierarchy": {"continent": 24865675, "country": 23424950, "town": 0, "planet": 1, "county": 12602124, "suburb": 0, "state": 12578034, "region": 0, "localadmin": 12693396}, "woe:timezone_id": 56043644, "woe:hash": "sp3e827ku1dv", "woe:centroid": [2.125, 41.398682], "geom:latitude": 41.398682, "geom:longitude": 2.125, "geom:hash": "sp3e827ku1dv", "woe:latitude": 41.398682, "geom:centroid": [2.125, 41.398682], "woe:longitude": 2.125, "woe:repo": "woeplanet-poi-es", "geom:area": 0.0, "woe:scale": 19}}