{"type": "Feature", "id": 23258202, "geometry": {"type": "Point", "coordinates": [2.17631, 41.410702]}, "properties": {"woe:id": 23258202, "woe:parent_id": 20220085, "woe:name": "Estaci\u00f3n de Hospital de Sant Pau", "woe:placetype": 20, "woe:placetype_name": "POI", "woe:lang": "UNK", "iso:country": "ES", "meta:provider": ["geoplanet:7.3.1", "geoplanet:7.3.2", "geoplanet:7.4.0", "geoplanet:7.4.1", "geoplanet:7.5.1", "geoplanet:7.5.2", "geoplanet:7.6.0", "geoplanet:7.8.1", "geoplanet:7.9.0", "geoplanet:7.10.0", "geoplanet:8.0.0", "woeplanet:8.0.0"], "meta:indexed": "2020-08-20T20:56:19.081553", "woe:alias_UNK_V": ["Estaci\u00f3n Hospital de Sant Pau", "Estaci\u00f3n del Hospital de Sant Pau"], "woe:alias_UNK_S": ["Estacion de Hospital de Sant Pau", "Estacion del Hospital de Sant Pau", "Estacion Hospital de Sant Pau"], "meta:updated": "2020-10-14T11:28:15.985010", "woe:hierarchy": {"continent": 24865675, "country": 23424950, "town": 0, "planet": 1, "county": 12602124, "suburb": 0, "state": 12578034, "region": 0, "localadmin": 12693396}, "woe:timezone_id": 56043644, "woe:hash": "sp3e9d8dzdq7", "woe:centroid": [2.17631, 41.410702], "geom:latitude": 41.410702, "geom:longitude": 2.17631, "geom:hash": "sp3e9d8dzdq7", "woe:latitude": 41.410702, "geom:centroid": [2.17631, 41.410702], "woe:longitude": 2.17631, "woe:repo": "woeplanet-poi-es", "geom:area": 0.0, "woe:scale": 19}}