{"type": "Feature", "id": 23236059, "geometry": {"type": "Point", "coordinates": [-5.99002, 37.396221]}, "properties": {"woe:id": 23236059, "woe:parent_id": 20220175, "woe:name": "Museo de Mu\u00f1ecas y Juguetes Antiguos", "woe:placetype": 20, "woe:placetype_name": "POI", "woe:lang": "SPA", "iso:country": "ES", "meta:provider": ["geoplanet:7.3.1", "geoplanet:7.3.2", "geoplanet:7.4.0", "geoplanet:7.4.1", "geoplanet:7.5.1", "geoplanet:7.5.2", "geoplanet:7.6.0", "geoplanet:7.8.1", "geoplanet:7.9.0", "geoplanet:7.10.0", "geoplanet:8.0.0", "woeplanet:8.0.0"], "meta:indexed": "2020-08-20T20:56:18.787702", "meta:updated": "2020-10-14T11:28:16.164132", "woe:alias_SPA_S": ["Museo de Munecas y Juguetes Antiguos", "Museo de Munyecas y Juguetes Antiguos"], "woe:hierarchy": {"continent": 24865675, "country": 23424950, "town": 0, "planet": 1, "county": 12602104, "suburb": 0, "state": 12578029, "region": 0, "localadmin": 12689383}, "woe:timezone_id": 56043644, "woe:hash": "eyesxxy0y2v7", "woe:centroid": [-5.99002, 37.396221], "geom:latitude": 37.396221, "geom:longitude": -5.99002, "geom:hash": "eyesxxy0y2v7", "woe:latitude": 37.396221, "geom:centroid": [-5.99002, 37.396221], "woe:longitude": -5.99002, "woe:repo": "woeplanet-poi-es", "geom:area": 0.0, "woe:scale": 19}}