{"type": "Feature", "id": 23233865, "geometry": {"type": "Point", "coordinates": [-4.10606, 36.726681]}, "properties": {"woe:id": 23233865, "woe:parent_id": 775705, "woe:name": "Desembocadura del R\u00edo V\u00e9lez", "woe:placetype": 20, "woe:placetype_name": "POI", "woe:lang": "SPA", "iso:country": "ES", "meta:provider": ["geoplanet:7.3.1", "geoplanet:7.3.2", "geoplanet:7.4.0", "geoplanet:7.4.1", "geoplanet:7.5.1", "geoplanet:7.5.2", "geoplanet:7.6.0", "geoplanet:7.8.1", "geoplanet:7.9.0", "geoplanet:7.10.0", "geoplanet:8.0.0", "woeplanet:8.0.0"], "meta:indexed": "2020-08-20T20:56:18.767302", "meta:updated": "2020-10-14T11:28:15.669417", "woe:alias_SPA_S": ["Desembocadura del Rio Velez"], "woe:hierarchy": {"continent": 24865675, "country": 23424950, "town": 0, "planet": 1, "county": 12602102, "suburb": 0, "state": 12578029, "region": 0, "localadmin": 12689283}, "woe:timezone_id": 56043644, "woe:hash": "eyt0ftfh3vec", "woe:centroid": [-4.10606, 36.726681], "geom:latitude": 36.726681, "geom:longitude": -4.10606, "geom:hash": "eyt0ftfh3vec", "woe:latitude": 36.726681, "geom:centroid": [-4.10606, 36.726681], "woe:longitude": -4.10606, "woe:repo": "woeplanet-poi-es", "geom:area": 0.0, "woe:scale": 19}}