{"type": "Feature", "id": 23240121, "geometry": {"type": "Point", "coordinates": [-8.40059, 43.37421]}, "properties": {"woe:id": 23240121, "woe:parent_id": 763246, "woe:name": "Museo Provincial de Belas Artes", "woe:placetype": 20, "woe:placetype_name": "POI", "woe:lang": "UNK", "iso:country": "ES", "meta:provider": ["geoplanet:7.3.1", "geoplanet:7.3.2", "geoplanet:7.4.0", "geoplanet:7.4.1", "geoplanet:7.5.1", "geoplanet:7.5.2", "geoplanet:7.6.0", "geoplanet:7.8.1", "geoplanet:7.9.0", "geoplanet:7.10.0", "geoplanet:8.0.0", "woeplanet:8.0.0"], "meta:indexed": "2020-08-20T20:56:18.841284", "meta:updated": "2020-10-14T11:28:16.190294", "woe:hierarchy": {"continent": 24865675, "country": 23424950, "town": 0, "planet": 1, "county": 12602130, "suburb": 0, "state": 12578036, "region": 0, "localadmin": 12694732}, "woe:timezone_id": 56043644, "woe:hash": "ezdnbb4ch4f0", "woe:centroid": [-8.40059, 43.37421], "geom:latitude": 43.37421, "geom:longitude": -8.40059, "geom:hash": "ezdnbb4ch4f0", "woe:latitude": 43.37421, "geom:centroid": [-8.40059, 43.37421], "woe:longitude": -8.40059, "woe:repo": "woeplanet-poi-es", "geom:area": 0.0, "woe:scale": 19}}