{"type": "Feature", "id": 56060779, "properties": {"woe:id": 56060779, "woe:parent_id": 20220219, "woe:name": "Univ. de Val\u00e8ncia Blasco Ib\u00e1\u00f1ez", "woe:placetype": 20, "woe:placetype_name": "POI", "woe:lang": "UNK", "iso:country": "ES", "meta:provider": ["geoplanet:7.3.1", "geoplanet:7.3.2", "geoplanet:7.4.0", "geoplanet:7.4.1", "geoplanet:7.5.1", "geoplanet:7.5.2", "geoplanet:7.6.0", "geoplanet:7.8.1", "geoplanet:7.9.0", "geoplanet:7.10.0", "geoplanet:8.0.0", "woeplanet:8.0.0"], "meta:indexed": "2020-08-20T20:56:20.104112", "woe:alias_UNK_V": ["Univ. de Valencia Blasco Ibanez"], "meta:updated": "2020-08-22T03:00:15.513620", "woe:hierarchy": {"continent": 24865675, "country": 23424950, "town": 0, "planet": 1, "county": 12602139, "suburb": 0, "state": 12578038, "region": 0, "localadmin": 12695789}, "woe:timezone_id": 56043644, "woe:hash": "ezp8xffsm68p", "woe:centroid": [-0.35889, 39.478741], "geom:latitude": 39.478741, "geom:longitude": -0.35889, "geom:hash": "ezp8xffsm68p", "woe:latitude": 39.478741, "geom:centroid": [-0.35889, 39.478741], "woe:longitude": -0.35889, "woe:repo": "woeplanet-poi-es"}, "geometry": {"coordinates": [-0.35889, 39.478741], "type": "Point"}}