{"type": "Feature", "id": 23265513, "geometry": {"type": "Point", "coordinates": [2.21843, 41.45192]}, "properties": {"woe:id": 23265513, "woe:parent_id": 773626, "woe:name": "Estaci\u00f3n de Fondo", "woe:placetype": 20, "woe:placetype_name": "POI", "woe:lang": "UNK", "iso:country": "ES", "meta:provider": ["geoplanet:7.3.1", "geoplanet:7.3.2", "geoplanet:7.4.0", "geoplanet:7.4.1", "geoplanet:7.5.1", "geoplanet:7.5.2", "geoplanet:7.6.0", "geoplanet:7.8.1", "geoplanet:7.9.0", "geoplanet:7.10.0", "geoplanet:8.0.0", "woeplanet:8.0.0"], "meta:indexed": "2020-08-20T20:56:19.290097", "woe:alias_UNK_V": ["Estaci\u00f3n Fondo", "Estaci\u00f3n del Fondo"], "woe:alias_UNK_S": ["Estacion de Fondo", "Estacion del Fondo", "Estacion Fondo"], "meta:updated": "2020-10-14T11:28:16.064969", "woe:hierarchy": {"continent": 24865675, "country": 23424950, "town": 0, "planet": 1, "county": 12602124, "suburb": 0, "state": 12578034, "region": 0, "localadmin": 12693625}, "woe:timezone_id": 56043644, "woe:hash": "sp3ef6p6vjvq", "woe:centroid": [2.21843, 41.45192], "geom:latitude": 41.45192, "geom:longitude": 2.21843, "geom:hash": "sp3ef6p6vjvq", "woe:latitude": 41.45192, "geom:centroid": [2.21843, 41.45192], "woe:longitude": 2.21843, "woe:repo": "woeplanet-poi-es", "geom:area": 0.0, "woe:scale": 19}}