{"type": "Feature", "id": 23246692, "properties": {"woe:id": 23246692, "woe:parent_id": 769112, "woe:name": "Estaci\u00f3n de Arga\u00f1osa-Lavapi\u00e9s", "woe:placetype": 20, "woe:placetype_name": "POI", "woe:lang": "SPA", "iso:country": "ES", "meta:provider": ["geoplanet:7.3.1", "geoplanet:7.3.2", "geoplanet:7.4.0", "geoplanet:7.4.1", "geoplanet:7.5.1", "geoplanet:7.5.2", "geoplanet:7.6.0", "geoplanet:7.8.1", "geoplanet:7.9.0", "geoplanet:7.10.0", "geoplanet:8.0.0", "woeplanet:8.0.0"], "meta:indexed": "2020-08-20T20:56:18.912468", "meta:updated": "2020-08-22T03:00:15.074032", "woe:alias_SPA_S": ["Estacion de Arganosa-Lavapies", "Estacion del Arganyosa-Lavapies", "Estacion Arganyosa-Lavapies", "Estacion de Arganyosa-Lavapies", "Estacion del Arganosa-Lavapies", "Estacion Arganosa-Lavapies"], "woe:alias_SPA_V": ["Estaci\u00f3n Arga\u00f1osa-Lavapi\u00e9s", "Estaci\u00f3n del Arga\u00f1osa-Lavapi\u00e9s"], "woe:hierarchy": {"continent": 24865675, "country": 23424950, "town": 0, "planet": 1, "county": 23388417, "suburb": 0, "state": 12578027, "region": 0, "localadmin": 12688486}, "woe:timezone_id": 56043644, "woe:hash": "ezeydq1p2g2j", "woe:centroid": [-5.87628, 43.3643], "geom:latitude": 43.3643, "geom:longitude": -5.87628, "geom:hash": "ezeydq1p2g2j", "woe:latitude": 43.3643, "geom:centroid": [-5.87628, 43.3643], "woe:longitude": -5.87628, "woe:repo": "woeplanet-poi-es"}, "geometry": {"coordinates": [-5.87628, 43.3643], "type": "Point"}}