{"type": "Feature", "id": 23229550, "properties": {"woe:id": 23229550, "woe:parent_id": 767586, "woe:name": "Poblado y Necr\u00f3polis Megal\u00edtica Pe\u00f1a de Los Gitanos", "woe:placetype": 20, "woe:placetype_name": "POI", "woe:lang": "SPA", "iso:country": "ES", "meta:provider": ["geoplanet:7.3.1", "geoplanet:7.3.2", "geoplanet:7.4.0", "geoplanet:7.4.1", "geoplanet:7.5.1", "geoplanet:7.5.2", "geoplanet:7.6.0", "geoplanet:7.8.1", "geoplanet:7.9.0", "geoplanet:7.10.0", "geoplanet:8.0.0", "woeplanet:8.0.0"], "meta:indexed": "2020-08-20T20:56:18.693723", "meta:updated": "2020-08-22T03:00:14.995712", "woe:alias_SPA_S": ["Poblado y Necropolis Megalitica Pena de Los Gitanos", "Poblado y Necropolis Megalitica Penya de Los Gitanos"], "woe:hierarchy": {"continent": 24865675, "country": 23424950, "town": 0, "planet": 1, "county": 12602099, "suburb": 0, "state": 12578029, "region": 0, "localadmin": 12688957}, "woe:timezone_id": 56043644, "woe:hash": "eythqh96x8rj", "woe:centroid": [-3.95303, 37.334721], "geom:latitude": 37.334721, "geom:longitude": -3.95303, "geom:hash": "eythqh96x8rj", "woe:latitude": 37.334721, "geom:centroid": [-3.95303, 37.334721], "woe:longitude": -3.95303, "woe:repo": "woeplanet-poi-es"}, "geometry": {"coordinates": [-3.95303, 37.334721], "type": "Point"}}