{"type": "Feature", "id": 23295491, "geometry": {"type": "Point", "coordinates": [-3.16855, 40.63382]}, "properties": {"woe:id": 23295491, "woe:parent_id": 761869, "woe:name": "Palacio de D\u00e1valos", "woe:placetype": 20, "woe:placetype_name": "POI", "woe:lang": "SPA", "iso:country": "ES", "meta:provider": ["geoplanet:7.3.1", "geoplanet:7.3.2", "geoplanet:7.4.0", "geoplanet:7.4.1", "geoplanet:7.5.1", "geoplanet:7.5.2", "geoplanet:7.6.0", "geoplanet:7.8.1", "geoplanet:7.9.0", "geoplanet:7.10.0", "geoplanet:8.0.0", "woeplanet:8.0.0"], "meta:indexed": "2020-08-20T20:56:19.768616", "meta:updated": "2020-10-14T11:28:15.389194", "woe:alias_SPA_S": ["Palacio de Davalos"], "woe:hierarchy": {"continent": 24865675, "country": 23424950, "town": 0, "planet": 1, "county": 12602113, "suburb": 0, "state": 12578032, "region": 0, "localadmin": 12690742}, "woe:timezone_id": 56043644, "woe:hash": "ezjxpvhtpmjc", "woe:centroid": [-3.16855, 40.63382], "geom:latitude": 40.63382, "geom:longitude": -3.16855, "geom:hash": "ezjxpvhtpmjc", "woe:latitude": 40.63382, "geom:centroid": [-3.16855, 40.63382], "woe:longitude": -3.16855, "woe:repo": "woeplanet-poi-es", "geom:area": 0.0, "woe:scale": 19}}