{"type": "Feature", "id": 56060824, "properties": {"woe:id": 56060824, "woe:parent_id": 20220219, "woe:name": "Facultad de Medicina", "woe:placetype": 20, "woe:placetype_name": "POI", "woe:lang": "SPA", "iso:country": "ES", "meta:provider": ["geoplanet:7.3.1", "geoplanet:7.3.2", "geoplanet:7.4.0", "geoplanet:7.4.1", "geoplanet:7.5.1", "geoplanet:7.5.2", "geoplanet:7.6.0", "geoplanet:7.8.1", "geoplanet:7.9.0", "geoplanet:7.10.0", "geoplanet:8.0.0", "woeplanet:8.0.0"], "meta:indexed": "2020-08-20T20:56:20.137014", "meta:updated": "2020-08-22T03:00:15.529644", "woe:hierarchy": {"continent": 24865675, "country": 23424950, "town": 0, "planet": 1, "county": 12602139, "suburb": 0, "state": 12578038, "region": 0, "localadmin": 12695789}, "woe:timezone_id": 56043644, "woe:hash": "ezp8xfb70ee4", "woe:centroid": [-0.36218, 39.478531], "geom:latitude": 39.478531, "geom:longitude": -0.36218, "geom:hash": "ezp8xfb70ee4", "woe:latitude": 39.478531, "geom:centroid": [-0.36218, 39.478531], "woe:longitude": -0.36218, "woe:repo": "woeplanet-poi-es"}, "geometry": {"coordinates": [-0.36218, 39.478531], "type": "Point"}}