{"type": "Feature", "id": 23256757, "properties": {"woe:id": 23256757, "woe:parent_id": 774129, "woe:name": "Estaci\u00f3n de les Corts", "woe:placetype": 20, "woe:placetype_name": "POI", "woe:lang": "UNK", "iso:country": "ES", "meta:provider": ["geoplanet:7.3.1", "geoplanet:7.3.2", "geoplanet:7.4.0", "geoplanet:7.4.1", "geoplanet:7.5.1", "geoplanet:7.5.2", "geoplanet:7.6.0", "geoplanet:7.8.1", "geoplanet:7.9.0", "geoplanet:7.10.0", "geoplanet:8.0.0", "woeplanet:8.0.0"], "meta:indexed": "2020-08-20T20:56:19.067010", "woe:alias_UNK_V": ["Estaci\u00f3n les Corts", "Estaci\u00f3n del les Corts"], "woe:alias_UNK_S": ["Estacion de les Corts", "Estacion del les Corts", "Estacion les Corts"], "meta:updated": "2020-08-22T03:00:15.131633", "woe:hierarchy": {"continent": 24865675, "country": 23424950, "town": 0, "planet": 1, "county": 12602124, "suburb": 0, "state": 12578034, "region": 0, "localadmin": 12693396}, "woe:timezone_id": 56043644, "woe:hash": "sp3e2mz8m0e7", "woe:centroid": [2.13088, 41.384171], "geom:latitude": 41.384171, "geom:longitude": 2.13088, "geom:hash": "sp3e2mz8m0e7", "woe:latitude": 41.384171, "geom:centroid": [2.13088, 41.384171], "woe:longitude": 2.13088, "woe:repo": "woeplanet-poi-es"}, "geometry": {"coordinates": [2.13088, 41.384171], "type": "Point"}}