{"type": "Feature", "id": 56060782, "properties": {"woe:id": 56060782, "woe:parent_id": 758719, "woe:name": "Zona Universit\u00e0ria", "woe:placetype": 20, "woe:placetype_name": "POI", "woe:lang": "UNK", "iso:country": "ES", "meta:provider": ["geoplanet:7.3.1", "geoplanet:7.3.2", "geoplanet:7.4.0", "geoplanet:7.4.1", "geoplanet:7.5.1", "geoplanet:7.5.2", "geoplanet:7.6.0", "geoplanet:7.8.1", "geoplanet:7.9.0", "geoplanet:7.10.0", "geoplanet:8.0.0", "woeplanet:8.0.0"], "meta:indexed": "2020-08-20T20:56:20.106554", "woe:alias_UNK_V": ["Zona Universitaria"], "meta:updated": "2020-08-22T03:00:15.515060", "woe:hierarchy": {"continent": 24865675, "country": 23424950, "town": 0, "planet": 1, "county": 12602124, "suburb": 0, "state": 12578034, "region": 0, "localadmin": 12693396}, "woe:timezone_id": 56043644, "woe:hash": "sp3e2juhyvcw", "woe:centroid": [2.11516, 41.384972], "geom:latitude": 41.384972, "geom:longitude": 2.11516, "geom:hash": "sp3e2juhyvcw", "woe:latitude": 41.384972, "geom:centroid": [2.11516, 41.384972], "woe:longitude": 2.11516, "woe:repo": "woeplanet-poi-es"}, "geometry": {"coordinates": [2.11516, 41.384972], "type": "Point"}}