{"type": "Feature", "id": 23261761, "geometry": {"type": "Point", "coordinates": [2.16066, 41.375011]}, "properties": {"woe:id": 23261761, "woe:parent_id": 20220095, "woe:name": "Estaci\u00f3n de Poble Sec", "woe:placetype": 20, "woe:placetype_name": "POI", "woe:lang": "UNK", "iso:country": "ES", "meta:provider": ["geoplanet:7.3.1", "geoplanet:7.3.2", "geoplanet:7.4.0", "geoplanet:7.4.1", "geoplanet:7.5.1", "geoplanet:7.5.2", "geoplanet:7.6.0", "geoplanet:7.8.1", "geoplanet:7.9.0", "geoplanet:7.10.0", "geoplanet:8.0.0", "woeplanet:8.0.0"], "meta:indexed": "2020-08-20T20:56:19.183974", "woe:alias_UNK_V": ["Estaci\u00f3n Poble Sec", "Estaci\u00f3n del Poble Sec"], "woe:alias_UNK_S": ["Estacion de Poble Sec", "Estacion del Poble Sec", "Estacion Poble Sec"], "meta:updated": "2020-10-14T11:28:16.301269", "woe:hierarchy": {"continent": 24865675, "country": 23424950, "town": 0, "planet": 1, "county": 12602124, "suburb": 0, "state": 12578034, "region": 0, "localadmin": 12693396}, "woe:timezone_id": 56043644, "woe:hash": "sp3e3hj6gj0f", "woe:centroid": [2.16066, 41.375011], "geom:latitude": 41.375011, "geom:longitude": 2.16066, "geom:hash": "sp3e3hj6gj0f", "woe:latitude": 41.375011, "geom:centroid": [2.16066, 41.375011], "woe:longitude": 2.16066, "woe:repo": "woeplanet-poi-es", "geom:area": 0.0, "woe:scale": 19}}