{"type": "Feature", "id": 23298187, "geometry": {"type": "Point", "coordinates": [-3.65189, 40.438412]}, "properties": {"woe:id": 23298187, "woe:parent_id": 20219853, "woe:name": "Estaci\u00f3n de Barrio de la Concepci\u00f3n", "woe:placetype": 20, "woe:placetype_name": "POI", "woe:lang": "SPA", "iso:country": "ES", "meta:provider": ["geoplanet:7.3.1", "geoplanet:7.3.2", "geoplanet:7.4.0", "geoplanet:7.4.1", "geoplanet:7.5.1", "geoplanet:7.5.2", "geoplanet:7.6.0", "geoplanet:7.8.1", "geoplanet:7.9.0", "geoplanet:7.10.0", "geoplanet:8.0.0", "woeplanet:8.0.0"], "meta:indexed": "2020-08-20T20:56:19.826877", "meta:updated": "2020-10-14T11:28:15.523821", "woe:alias_SPA_S": ["Estacion de Barrio de la Concepcion", "Estacion del Barrio de la Concepcion", "Estacion Barrio de la Concepcion"], "woe:alias_SPA_V": ["Estaci\u00f3n Barrio de la Concepci\u00f3n", "Estaci\u00f3n del Barrio de la Concepci\u00f3n"], "woe:hierarchy": {"continent": 24865675, "country": 23424950, "town": 0, "planet": 1, "county": 12602090, "suburb": 0, "state": 12578024, "region": 0, "localadmin": 12688024}, "woe:timezone_id": 56043644, "woe:hash": "ezjqhcsfbf37", "woe:centroid": [-3.65189, 40.438412], "geom:latitude": 40.438412, "geom:longitude": -3.65189, "geom:hash": "ezjqhcsfbf37", "woe:latitude": 40.438412, "geom:centroid": [-3.65189, 40.438412], "woe:longitude": -3.65189, "woe:repo": "woeplanet-poi-es", "geom:area": 0.0, "woe:scale": 19}}