{"type": "Feature", "id": 22408894, "properties": {"woe:id": 22408894, "woe:parent_id": 29370530, "woe:name": "Estaci\u00f3n de Royales-Benofojor", "woe:placetype": 20, "woe:placetype_name": "POI", "woe:lang": "SPA", "iso:country": "ES", "meta:provider": ["geoplanet:7.3.1", "geoplanet:7.3.2", "geoplanet:7.4.0", "geoplanet:7.4.1", "geoplanet:7.5.1", "geoplanet:7.5.2", "geoplanet:7.6.0", "geoplanet:7.8.1", "geoplanet:7.9.0", "geoplanet:7.10.0", "geoplanet:8.0.0", "woeplanet:8.0.0"], "meta:indexed": "2020-08-20T20:56:18.432169", "meta:updated": "2020-08-22T03:00:14.896621", "woe:alias_SPA_S": ["Estacion de Royales-Benofojor", "Estacion del Royales-Benofojor", "Estacion Royales-Benofojor"], "woe:alias_SPA_V": ["Estaci\u00f3n Royales-Benofojor", "Estaci\u00f3n del Royales-Benofojor"], "woe:hierarchy": {"continent": 24865675, "country": 23424950, "town": 0, "planet": 1, "county": 12602137, "suburb": 0, "state": 12578038, "region": 0, "localadmin": 12695277}, "woe:timezone_id": 56043644, "woe:hash": "eyz2x12hv9e4", "woe:centroid": [-0.74683, 38.064331], "geom:latitude": 38.064331, "geom:longitude": -0.74683, "geom:hash": "eyz2x12hv9e4", "woe:latitude": 38.064331, "geom:centroid": [-0.74683, 38.064331], "woe:longitude": -0.74683, "woe:repo": "woeplanet-poi-es"}, "geometry": {"coordinates": [-0.74683, 38.064331], "type": "Point"}}