{"type": "Feature", "id": 23289693, "properties": {"woe:id": 23289693, "woe:parent_id": 776390, "woe:name": "Estaci\u00f3n de Utiel", "woe:placetype": 20, "woe:placetype_name": "POI", "woe:lang": "SPA", "iso:country": "ES", "meta:provider": ["geoplanet:7.3.1", "geoplanet:7.3.2", "geoplanet:7.4.0", "geoplanet:7.4.1", "geoplanet:7.5.1", "geoplanet:7.5.2", "geoplanet:7.6.0", "geoplanet:7.8.1", "geoplanet:7.9.0", "geoplanet:7.10.0", "geoplanet:8.0.0", "woeplanet:8.0.0"], "meta:indexed": "2020-08-20T20:56:19.697263", "meta:updated": "2020-08-22T03:00:15.360333", "woe:alias_SPA_S": ["Estacion de Utiel", "Estacion del Utiel", "Estacion Utiel"], "woe:alias_SPA_V": ["Estaci\u00f3n Utiel", "Estaci\u00f3n del Utiel"], "woe:hierarchy": {"continent": 24865675, "country": 23424950, "town": 0, "planet": 1, "county": 12602139, "suburb": 0, "state": 12578038, "region": 0, "localadmin": 12695788}, "woe:timezone_id": 56043644, "woe:hash": "ezp1heezqtmm", "woe:centroid": [-1.20306, 39.571281], "geom:latitude": 39.571281, "geom:longitude": -1.20306, "geom:hash": "ezp1heezqtmm", "woe:latitude": 39.571281, "geom:centroid": [-1.20306, 39.571281], "woe:longitude": -1.20306, "woe:repo": "woeplanet-poi-es"}, "geometry": {"coordinates": [-1.20306, 39.571281], "type": "Point"}}