{"type": "Feature", "id": 23284309, "geometry": {"type": "Point", "coordinates": [-0.98609, 37.59816]}, "properties": {"woe:id": 23284309, "woe:parent_id": 756324, "woe:name": "Monumento A Los H\u00e9roes de la Cavite", "woe:placetype": 20, "woe:placetype_name": "POI", "woe:lang": "SPA", "iso:country": "ES", "meta:provider": ["geoplanet:7.3.1", "geoplanet:7.3.2", "geoplanet:7.4.0", "geoplanet:7.4.1", "geoplanet:7.5.1", "geoplanet:7.5.2", "geoplanet:7.6.0", "geoplanet:7.8.1", "geoplanet:7.9.0", "geoplanet:7.10.0", "geoplanet:8.0.0", "woeplanet:8.0.0"], "meta:indexed": "2020-08-20T20:56:19.591478", "meta:updated": "2020-10-14T11:28:16.057154", "woe:alias_SPA_S": ["Monumento A Los Heroes de la Cavite"], "woe:hierarchy": {"continent": 24865675, "country": 23424950, "town": 0, "planet": 1, "county": 12602091, "suburb": 0, "state": 12578025, "region": 0, "localadmin": 12688141}, "woe:timezone_id": 56043644, "woe:hash": "eyxmcs9cnmn0", "woe:centroid": [-0.98609, 37.59816], "geom:latitude": 37.59816, "geom:longitude": -0.98609, "geom:hash": "eyxmcs9cnmn0", "woe:latitude": 37.59816, "geom:centroid": [-0.98609, 37.59816], "woe:longitude": -0.98609, "woe:repo": "woeplanet-poi-es", "geom:area": 0.0, "woe:scale": 19}}