{"type": "Feature", "id": 23224098, "geometry": {"type": "Point", "coordinates": [-6.38566, 39.46122]}, "properties": {"woe:id": 23224098, "woe:parent_id": 755379, "woe:name": "Estaci\u00f3n de C\u00e1ceres", "woe:placetype": 20, "woe:placetype_name": "POI", "woe:lang": "SPA", "iso:country": "ES", "meta:provider": ["geoplanet:7.3.1", "geoplanet:7.3.2", "geoplanet:7.4.0", "geoplanet:7.4.1", "geoplanet:7.5.1", "geoplanet:7.5.2", "geoplanet:7.6.0", "geoplanet:7.8.1", "geoplanet:7.9.0", "geoplanet:7.10.0", "geoplanet:8.0.0", "woeplanet:8.0.0"], "meta:indexed": "2020-08-20T20:56:18.631542", "meta:updated": "2020-10-14T11:28:15.600243", "woe:alias_SPA_S": ["Estacion de Caceres", "Estacion del Caceres", "Estacion Caceres"], "woe:alias_SPA_V": ["Estaci\u00f3n C\u00e1ceres", "Estaci\u00f3n del C\u00e1ceres"], "woe:hierarchy": {"continent": 24865675, "country": 23424950, "town": 0, "planet": 1, "county": 12602129, "suburb": 0, "state": 12578035, "region": 0, "localadmin": 12694519}, "woe:timezone_id": 56043644, "woe:hash": "ez52qxwn72df", "woe:centroid": [-6.38566, 39.46122], "geom:latitude": 39.46122, "geom:longitude": -6.38566, "geom:hash": "ez52qxwn72df", "woe:latitude": 39.46122, "geom:centroid": [-6.38566, 39.46122], "woe:longitude": -6.38566, "woe:repo": "woeplanet-poi-es", "geom:area": 0.0, "woe:scale": 19}}