{"type": "Feature", "id": 23255970, "geometry": {"type": "Point", "coordinates": [2.18046, 41.423531]}, "properties": {"woe:id": 23255970, "woe:parent_id": 20220082, "woe:name": "Estaci\u00f3n de Congreso", "woe:placetype": 20, "woe:placetype_name": "POI", "woe:lang": "SPA", "iso:country": "ES", "meta:provider": ["geoplanet:7.3.1", "geoplanet:7.3.2", "geoplanet:7.4.0", "geoplanet:7.4.1", "geoplanet:7.5.1", "geoplanet:7.5.2", "geoplanet:7.6.0", "geoplanet:7.8.1", "geoplanet:7.9.0", "geoplanet:7.10.0", "geoplanet:8.0.0", "woeplanet:8.0.0"], "meta:indexed": "2020-08-20T20:56:19.044099", "meta:updated": "2020-10-14T11:28:15.833634", "woe:alias_SPA_S": ["Estacion de Congreso", "Estacion del Congreso", "Estacion Congreso"], "woe:alias_SPA_V": ["Estaci\u00f3n Congreso", "Estaci\u00f3n del Congreso"], "woe:hierarchy": {"continent": 24865675, "country": 23424950, "town": 0, "planet": 1, "county": 12602124, "suburb": 0, "state": 12578034, "region": 0, "localadmin": 12693396}, "woe:timezone_id": 56043644, "woe:hash": "sp3e9sgv83ug", "woe:centroid": [2.18046, 41.423531], "geom:latitude": 41.423531, "geom:longitude": 2.18046, "geom:hash": "sp3e9sgv83ug", "woe:latitude": 41.423531, "geom:centroid": [2.18046, 41.423531], "woe:longitude": 2.18046, "woe:repo": "woeplanet-poi-es", "geom:area": 0.0, "woe:scale": 19}}