{"type": "Feature", "id": 23269828, "geometry": {"type": "Point", "coordinates": [0.96788, 41.637909]}, "properties": {"woe:id": 23269828, "woe:parent_id": 756798, "woe:name": "Estaci\u00f3n de Castellnou de Seana", "woe:placetype": 20, "woe:placetype_name": "POI", "woe:lang": "UNK", "iso:country": "ES", "meta:provider": ["geoplanet:7.3.1", "geoplanet:7.3.2", "geoplanet:7.4.0", "geoplanet:7.4.1", "geoplanet:7.5.1", "geoplanet:7.5.2", "geoplanet:7.6.0", "geoplanet:7.8.1", "geoplanet:7.9.0", "geoplanet:7.10.0", "geoplanet:8.0.0", "woeplanet:8.0.0"], "meta:indexed": "2020-08-20T20:56:19.384299", "woe:alias_UNK_V": ["Estaci\u00f3n Castellnou de Seana", "Estaci\u00f3n del Castellnou de Seana"], "woe:alias_UNK_S": ["Estacion de Castellnou de Seana", "Estacion del Castellnou de Seana", "Estacion Castellnou de Seana"], "meta:updated": "2020-10-14T11:28:16.221272", "woe:hierarchy": {"continent": 24865675, "country": 23424950, "town": 0, "planet": 1, "county": 12602126, "suburb": 0, "state": 12578034, "region": 0, "localadmin": 12693967}, "woe:timezone_id": 56043644, "woe:hash": "sp2sy5by3hz9", "woe:centroid": [0.96788, 41.637909], "geom:latitude": 41.637909, "geom:longitude": 0.96788, "geom:hash": "sp2sy5by3hz9", "woe:latitude": 41.637909, "geom:centroid": [0.96788, 41.637909], "woe:longitude": 0.96788, "woe:repo": "woeplanet-poi-es", "geom:area": 0.0, "woe:scale": 19}}