{"type": "Feature", "id": 56060778, "geometry": {"type": "Point", "coordinates": [-0.06786, 39.995369]}, "properties": {"woe:id": 56060778, "woe:parent_id": 756804, "woe:name": "Universitat Jaume I", "woe:placetype": 20, "woe:placetype_name": "POI", "woe:lang": "UNK", "iso:country": "ES", "meta:provider": ["geoplanet:7.3.1", "geoplanet:7.3.2", "geoplanet:7.4.0", "geoplanet:7.4.1", "geoplanet:7.5.1", "geoplanet:7.5.2", "geoplanet:7.6.0", "geoplanet:7.8.1", "geoplanet:7.9.0", "geoplanet:7.10.0", "geoplanet:8.0.0", "woeplanet:8.0.0"], "meta:indexed": "2020-08-20T20:56:20.103289", "meta:updated": "2020-10-14T11:28:19.419241", "woe:hierarchy": {"continent": 24865675, "country": 23424950, "town": 0, "planet": 1, "county": 12602138, "suburb": 0, "state": 12578038, "region": 0, "localadmin": 12695443}, "woe:timezone_id": 56043644, "woe:hash": "ezpgw2ytftpv", "woe:centroid": [-0.06786, 39.995369], "geom:latitude": 39.995369, "geom:longitude": -0.06786, "geom:hash": "ezpgw2ytftpv", "woe:latitude": 39.995369, "geom:centroid": [-0.06786, 39.995369], "woe:longitude": -0.06786, "woe:repo": "woeplanet-poi-es", "geom:area": 0.0, "woe:scale": 19}}