{"type": "Feature", "id": 22410294, "geometry": {"type": "Point", "coordinates": [-0.13421, 38.547939]}, "properties": {"woe:id": 22410294, "woe:parent_id": 754255, "woe:name": "Estaci\u00f3n de Benidorm", "woe:placetype": 20, "woe:placetype_name": "POI", "woe:lang": "SPA", "iso:country": "ES", "meta:provider": ["geoplanet:7.3.1", "geoplanet:7.3.2", "geoplanet:7.4.0", "geoplanet:7.4.1", "geoplanet:7.5.1", "geoplanet:7.5.2", "geoplanet:7.6.0", "geoplanet:7.8.1", "geoplanet:7.9.0", "geoplanet:7.10.0", "geoplanet:8.0.0", "woeplanet:8.0.0"], "meta:indexed": "2020-08-20T20:56:18.441764", "meta:updated": "2020-10-14T11:28:19.349805", "woe:alias_SPA_S": ["Estacion de Benidorm", "Estacion del Benidorm", "Estacion Benidorm"], "woe:alias_SPA_V": ["Estaci\u00f3n Benidorm", "Estaci\u00f3n del Benidorm"], "woe:hierarchy": {"continent": 24865675, "country": 23424950, "town": 0, "planet": 1, "county": 12602137, "suburb": 0, "state": 12578038, "region": 0, "localadmin": 12695296}, "woe:timezone_id": 56043644, "woe:hash": "eyzgkcqq08tu", "woe:centroid": [-0.13421, 38.547939], "geom:latitude": 38.547939, "geom:longitude": -0.13421, "geom:hash": "eyzgkcqq08tu", "woe:latitude": 38.547939, "geom:centroid": [-0.13421, 38.547939], "woe:longitude": -0.13421, "woe:repo": "woeplanet-poi-es", "geom:area": 0.0, "woe:scale": 19}}