{"type": "Feature", "id": 23312858, "properties": {"woe:id": 23312858, "woe:parent_id": 775524, "woe:name": "Centro Cultural Padilla", "woe:placetype": 20, "woe:placetype_name": "POI", "woe:lang": "SPA", "iso:country": "ES", "meta:provider": ["geoplanet:7.3.1", "geoplanet:7.3.2", "geoplanet:7.4.0", "geoplanet:7.4.1", "geoplanet:7.5.1", "geoplanet:7.5.2", "geoplanet:7.6.0", "geoplanet:7.8.1", "geoplanet:7.9.0", "geoplanet:7.10.0", "geoplanet:8.0.0", "woeplanet:8.0.0"], "meta:indexed": "2020-08-20T20:56:19.981577", "meta:updated": "2020-08-22T03:00:15.478254", "woe:hierarchy": {"continent": 24865675, "country": 23424950, "town": 0, "planet": 1, "county": 12602114, "suburb": 0, "state": 12578032, "region": 0, "localadmin": 12691090}, "woe:timezone_id": 56043644, "woe:hash": "ezj4u25h5w3d", "woe:centroid": [-4.02771, 39.859119], "geom:latitude": 39.859119, "geom:longitude": -4.02771, "geom:hash": "ezj4u25h5w3d", "woe:latitude": 39.859119, "geom:centroid": [-4.02771, 39.859119], "woe:longitude": -4.02771, "woe:repo": "woeplanet-poi-es"}, "geometry": {"coordinates": [-4.02771, 39.859119], "type": "Point"}}