{"type": "Feature", "id": 23231372, "geometry": {"type": "Point", "coordinates": [-4.47873, 37.17635]}, "properties": {"woe:id": 23231372, "woe:parent_id": 15003636, "woe:name": "Necr\u00f3polis", "woe:placetype": 20, "woe:placetype_name": "POI", "woe:lang": "SPA", "iso:country": "ES", "meta:provider": ["geoplanet:7.3.1", "geoplanet:7.3.2", "geoplanet:7.4.0", "geoplanet:7.4.1", "geoplanet:7.5.1", "geoplanet:7.5.2", "geoplanet:7.6.0", "geoplanet:7.8.1", "geoplanet:7.9.0", "geoplanet:7.10.0", "geoplanet:8.0.0", "woeplanet:8.0.0"], "meta:indexed": "2020-08-20T20:56:18.722920", "meta:updated": "2020-10-14T11:28:16.034719", "woe:alias_SPA_S": ["Necropolis"], "woe:hierarchy": {"continent": 24865675, "country": 23424950, "town": 0, "planet": 1, "county": 12602102, "suburb": 0, "state": 12578029, "region": 0, "localadmin": 12689204}, "woe:timezone_id": 56043644, "woe:hash": "eysg6pdxyjbv", "woe:centroid": [-4.47873, 37.17635], "geom:latitude": 37.17635, "geom:longitude": -4.47873, "geom:hash": "eysg6pdxyjbv", "woe:latitude": 37.17635, "geom:centroid": [-4.47873, 37.17635], "woe:longitude": -4.47873, "woe:repo": "woeplanet-poi-es", "geom:area": 0.0, "woe:scale": 19}}