{"type": "Feature", "id": 23223686, "geometry": {"type": "Point", "coordinates": [-6.3415, 38.911041]}, "properties": {"woe:id": 23223686, "woe:parent_id": 767100, "woe:name": "Casa de Mitreo", "woe:placetype": 20, "woe:placetype_name": "POI", "woe:lang": "SPA", "iso:country": "ES", "meta:provider": ["geoplanet:7.4.0", "geoplanet:7.4.1", "geoplanet:7.5.1", "geoplanet:7.5.2", "geoplanet:7.6.0", "geoplanet:7.8.1", "geoplanet:7.9.0", "geoplanet:7.10.0", "geoplanet:8.0.0", "woeplanet:8.0.0"], "meta:indexed": "2020-08-20T23:48:49.634518", "meta:updated": "2020-10-14T11:28:15.682576", "woe:hierarchy": {"continent": 24865675, "country": 23424950, "town": 0, "planet": 1, "county": 12602128, "suburb": 0, "state": 12578035, "region": 0, "localadmin": 12694402}, "woe:timezone_id": 56043644, "woe:hash": "eygmrew30rfb", "woe:centroid": [-6.3415, 38.911041], "geom:latitude": 38.911041, "geom:longitude": -6.3415, "geom:hash": "eygmrew30rfb", "woe:latitude": 38.911041, "geom:centroid": [-6.3415, 38.911041], "woe:longitude": -6.3415, "woe:repo": "woeplanet-poi-es", "geom:area": 0.0, "woe:scale": 19}}