{"type": "Feature", "id": 22414818, "properties": {"woe:id": 22414818, "woe:parent_id": 20219885, "woe:name": "Estaci\u00f3n de Sevilla", "woe:placetype": 20, "woe:placetype_name": "POI", "woe:lang": "SPA", "iso:country": "ES", "meta:provider": ["geoplanet:7.3.1", "geoplanet:7.3.2", "geoplanet:7.4.0", "geoplanet:7.4.1", "geoplanet:7.5.1", "geoplanet:7.5.2", "geoplanet:7.6.0", "geoplanet:7.8.1", "geoplanet:7.9.0", "geoplanet:7.10.0", "geoplanet:8.0.0", "woeplanet:8.0.0"], "meta:indexed": "2020-08-20T20:56:18.548480", "meta:updated": "2020-08-22T03:00:14.939456", "woe:alias_SPA_S": ["Estacion de Sevilla", "Estacion del Sevilla", "Estacion Sevilla"], "woe:alias_SPA_V": ["Estaci\u00f3n Sevilla", "Estaci\u00f3n del Sevilla"], "woe:hierarchy": {"continent": 24865675, "country": 23424950, "town": 0, "planet": 1, "county": 12602090, "suburb": 0, "state": 12578024, "region": 0, "localadmin": 12688024}, "woe:timezone_id": 56043644, "woe:hash": "ezjmgvgq4bc0", "woe:centroid": [-3.69781, 40.418362], "geom:latitude": 40.418362, "geom:longitude": -3.69781, "geom:hash": "ezjmgvgq4bc0", "woe:latitude": 40.418362, "geom:centroid": [-3.69781, 40.418362], "woe:longitude": -3.69781, "woe:repo": "woeplanet-poi-es"}, "geometry": {"coordinates": [-3.69781, 40.418362], "type": "Point"}}