{"type": "Feature", "id": 23262556, "geometry": {"type": "Point", "coordinates": [1.7253, 41.37112]}, "properties": {"woe:id": 23262556, "woe:parent_id": 763462, "woe:name": "Estaci\u00f3n de la Granada", "woe:placetype": 20, "woe:placetype_name": "POI", "woe:lang": "UNK", "iso:country": "ES", "meta:provider": ["geoplanet:7.3.1", "geoplanet:7.3.2", "geoplanet:7.4.0", "geoplanet:7.4.1", "geoplanet:7.5.1", "geoplanet:7.5.2", "geoplanet:7.6.0", "geoplanet:7.8.1", "geoplanet:7.9.0", "geoplanet:7.10.0", "geoplanet:8.0.0", "woeplanet:8.0.0"], "meta:indexed": "2020-08-20T20:56:19.206547", "woe:alias_UNK_V": ["Estaci\u00f3n la Granada", "Estaci\u00f3n del la Granada"], "woe:alias_UNK_S": ["Estacion de la Granada", "Estacion del la Granada", "Estacion la Granada"], "meta:updated": "2020-10-14T11:28:15.715386", "woe:hierarchy": {"continent": 24865675, "country": 23424950, "town": 0, "planet": 1, "county": 12602124, "suburb": 0, "state": 12578034, "region": 0, "localadmin": 12693474}, "woe:timezone_id": 56043644, "woe:hash": "sp35r72k4rsz", "woe:centroid": [1.7253, 41.37112], "geom:latitude": 41.37112, "geom:longitude": 1.7253, "geom:hash": "sp35r72k4rsz", "woe:latitude": 41.37112, "geom:centroid": [1.7253, 41.37112], "woe:longitude": 1.7253, "woe:repo": "woeplanet-poi-es", "geom:area": 0.0, "woe:scale": 19}}