{"type": "Feature", "id": 23248438, "geometry": {"type": "Point", "coordinates": [-8.68189, 42.403542]}, "properties": {"woe:id": 23248438, "woe:parent_id": 29372424, "woe:name": "Ruinas de Santo Domingo", "woe:placetype": 20, "woe:placetype_name": "POI", "woe:lang": "SPA", "iso:country": "ES", "meta:provider": ["geoplanet:7.3.1", "geoplanet:7.3.2", "geoplanet:7.4.0", "geoplanet:7.4.1", "geoplanet:7.5.1", "geoplanet:7.5.2", "geoplanet:7.6.0", "geoplanet:7.8.1", "geoplanet:7.9.0", "geoplanet:7.10.0", "geoplanet:8.0.0", "woeplanet:8.0.0"], "meta:indexed": "2020-08-20T20:56:18.922982", "meta:updated": "2020-10-14T11:28:15.885506", "woe:hierarchy": {"continent": 24865675, "country": 23424950, "town": 0, "planet": 1, "county": 12602133, "suburb": 0, "state": 12578036, "region": 0, "localadmin": 12694996}, "woe:timezone_id": 56043644, "woe:hash": "ez9c4rq4931s", "woe:centroid": [-8.68189, 42.403542], "geom:latitude": 42.403542, "geom:longitude": -8.68189, "geom:hash": "ez9c4rq4931s", "woe:latitude": 42.403542, "geom:centroid": [-8.68189, 42.403542], "woe:longitude": -8.68189, "woe:repo": "woeplanet-poi-es", "geom:area": 0.0, "woe:scale": 19}}