{"type": "Feature", "id": 23266366, "properties": {"woe:id": 23266366, "woe:parent_id": 23413580, "woe:name": "Estaci\u00f3n de Vacarisses", "woe:placetype": 20, "woe:placetype_name": "POI", "woe:lang": "SPA", "iso:country": "ES", "meta:provider": ["geoplanet:7.3.1", "geoplanet:7.3.2", "geoplanet:7.4.0", "geoplanet:7.4.1", "geoplanet:7.5.1", "geoplanet:7.5.2", "geoplanet:7.6.0", "geoplanet:7.8.1", "geoplanet:7.9.0", "geoplanet:7.10.0", "geoplanet:8.0.0", "woeplanet:8.0.0"], "meta:indexed": "2020-08-20T20:56:19.316276", "meta:updated": "2020-08-22T03:00:15.213938", "woe:alias_SPA_S": ["Estacion de Vacarisses", "Estacion del Vacarisses", "Estacion Vacarisses"], "woe:alias_SPA_V": ["Estaci\u00f3n Vacarisses", "Estaci\u00f3n del Vacarisses"], "woe:hierarchy": {"continent": 24865675, "country": 23424950, "town": 0, "planet": 1, "county": 12602124, "suburb": 0, "state": 12578034, "region": 0, "localadmin": 12693665}, "woe:timezone_id": 56043644, "woe:hash": "sp3kehv5gt5x", "woe:centroid": [1.89667, 41.59903], "geom:latitude": 41.59903, "geom:longitude": 1.89667, "geom:hash": "sp3kehv5gt5x", "woe:latitude": 41.59903, "geom:centroid": [1.89667, 41.59903], "woe:longitude": 1.89667, "woe:repo": "woeplanet-poi-es"}, "geometry": {"coordinates": [1.89667, 41.59903], "type": "Point"}}