{"type": "Feature", "id": 23296914, "properties": {"woe:id": 23296914, "woe:parent_id": 757273, "woe:name": "Estaci\u00f3n de Cercedilla", "woe:placetype": 20, "woe:placetype_name": "POI", "woe:lang": "SPA", "iso:country": "ES", "meta:provider": ["geoplanet:7.3.1", "geoplanet:7.3.2", "geoplanet:7.4.0", "geoplanet:7.4.1", "geoplanet:7.5.1", "geoplanet:7.5.2", "geoplanet:7.6.0", "geoplanet:7.8.1", "geoplanet:7.9.0", "geoplanet:7.10.0", "geoplanet:8.0.0", "woeplanet:8.0.0"], "meta:indexed": "2020-08-20T20:56:19.797198", "meta:updated": "2020-08-22T03:00:15.400053", "woe:alias_SPA_S": ["Estacion de Cercedilla", "Estacion del Cercedilla", "Estacion Cercedilla"], "woe:alias_SPA_V": ["Estaci\u00f3n Cercedilla", "Estaci\u00f3n del Cercedilla"], "woe:hierarchy": {"continent": 24865675, "country": 23424950, "town": 0, "planet": 1, "county": 12602090, "suburb": 0, "state": 12578024, "region": 0, "localadmin": 12687983}, "woe:timezone_id": 56043644, "woe:hash": "ezjpg2nchs5x", "woe:centroid": [-4.06646, 40.737499], "geom:latitude": 40.737499, "geom:longitude": -4.06646, "geom:hash": "ezjpg2nchs5x", "woe:latitude": 40.737499, "geom:centroid": [-4.06646, 40.737499], "woe:longitude": -4.06646, "woe:repo": "woeplanet-poi-es"}, "geometry": {"coordinates": [-4.06646, 40.737499], "type": "Point"}}