{"type": "Feature", "id": 23263946, "geometry": {"type": "Point", "coordinates": [2.28631, 41.468578]}, "properties": {"woe:id": 23263946, "woe:parent_id": 767466, "woe:name": "Estaci\u00f3n de Baixador Monsolis", "woe:placetype": 20, "woe:placetype_name": "POI", "woe:lang": "UNK", "iso:country": "ES", "meta:provider": ["geoplanet:7.3.1", "geoplanet:7.3.2", "geoplanet:7.4.0", "geoplanet:7.4.1", "geoplanet:7.5.1", "geoplanet:7.5.2", "geoplanet:7.6.0", "geoplanet:7.8.1", "geoplanet:7.9.0", "geoplanet:7.10.0", "geoplanet:8.0.0", "woeplanet:8.0.0"], "meta:indexed": "2020-08-20T20:56:19.246364", "woe:alias_UNK_V": ["Estaci\u00f3n Baixador Monsolis", "Estaci\u00f3n del Baixador Monsolis"], "woe:alias_UNK_S": ["Estacion de Baixador Monsolis", "Estacion del Baixador Monsolis", "Estacion Baixador Monsolis"], "meta:updated": "2020-10-14T11:28:15.879061", "woe:hierarchy": {"continent": 24865675, "country": 23424950, "town": 0, "planet": 1, "county": 12602124, "suburb": 0, "state": 12578034, "region": 0, "localadmin": 12693512}, "woe:timezone_id": 56043644, "woe:hash": "sp3euj0gfzhr", "woe:centroid": [2.28631, 41.468578], "geom:latitude": 41.468578, "geom:longitude": 2.28631, "geom:hash": "sp3euj0gfzhr", "woe:latitude": 41.468578, "geom:centroid": [2.28631, 41.468578], "woe:longitude": 2.28631, "woe:repo": "woeplanet-poi-es", "geom:area": 0.0, "woe:scale": 19}}