{"type": "Feature", "id": 23284751, "properties": {"woe:id": 23284751, "woe:parent_id": 765531, "woe:name": "Iglesia de San Pedro", "woe:placetype": 20, "woe:placetype_name": "POI", "woe:lang": "SPA", "iso:country": "ES", "meta:provider": ["geoplanet:7.3.1", "geoplanet:7.3.2", "geoplanet:7.4.0", "geoplanet:7.4.1", "geoplanet:7.5.1", "geoplanet:7.5.2", "geoplanet:7.6.0", "geoplanet:7.8.1", "geoplanet:7.9.0", "geoplanet:7.10.0", "geoplanet:8.0.0", "woeplanet:8.0.0"], "meta:indexed": "2020-08-20T20:56:19.604891", "meta:updated": "2020-08-22T03:00:15.326502", "woe:hierarchy": {"continent": 24865675, "country": 23424950, "town": 0, "planet": 1, "county": 12602091, "suburb": 0, "state": 12578025, "region": 0, "localadmin": 12688149}, "woe:timezone_id": 56043644, "woe:hash": "eywy36bdm2w8", "woe:centroid": [-1.70196, 37.676628], "geom:latitude": 37.676628, "geom:longitude": -1.70196, "geom:hash": "eywy36bdm2w8", "woe:latitude": 37.676628, "geom:centroid": [-1.70196, 37.676628], "woe:longitude": -1.70196, "woe:repo": "woeplanet-poi-es"}, "geometry": {"coordinates": [-1.70196, 37.676628], "type": "Point"}}