{"type": "Feature", "id": 23290727, "geometry": {"type": "Point", "coordinates": [-0.38907, 39.476261]}, "properties": {"woe:id": 23290727, "woe:parent_id": 20220215, "woe:name": "Ciencias Naturales P. Ignacio Sala S. J.", "woe:placetype": 20, "woe:placetype_name": "POI", "woe:lang": "SPA", "iso:country": "ES", "meta:provider": ["geoplanet:7.3.1", "geoplanet:7.3.2", "geoplanet:7.4.0", "geoplanet:7.4.1", "geoplanet:7.5.1", "geoplanet:7.5.2", "geoplanet:7.6.0", "geoplanet:7.8.1", "geoplanet:7.9.0", "geoplanet:7.10.0", "geoplanet:8.0.0", "woeplanet:8.0.0"], "meta:indexed": "2020-08-20T20:56:19.715820", "meta:updated": "2020-10-14T11:28:15.475858", "woe:hierarchy": {"continent": 24865675, "country": 23424950, "town": 0, "planet": 1, "county": 12602139, "suburb": 0, "state": 12578038, "region": 0, "localadmin": 12695789}, "woe:timezone_id": 56043644, "woe:hash": "ezp8x4ktyh2m", "woe:centroid": [-0.38907, 39.476261], "geom:latitude": 39.476261, "geom:longitude": -0.38907, "geom:hash": "ezp8x4ktyh2m", "woe:latitude": 39.476261, "geom:centroid": [-0.38907, 39.476261], "woe:longitude": -0.38907, "woe:repo": "woeplanet-poi-es", "geom:area": 0.0, "woe:scale": 19}}