{"type": "Feature", "id": 22414614, "properties": {"woe:id": 22414614, "woe:parent_id": 20219944, "woe:name": "Estaci\u00f3n de Cuatro Vientos", "woe:placetype": 20, "woe:placetype_name": "POI", "woe:lang": "SPA", "iso:country": "ES", "meta:provider": ["geoplanet:7.3.1", "geoplanet:7.3.2", "geoplanet:7.4.0", "geoplanet:7.4.1", "geoplanet:7.5.1", "geoplanet:7.5.2", "geoplanet:7.6.0", "geoplanet:7.8.1", "geoplanet:7.9.0", "geoplanet:7.10.0", "geoplanet:8.0.0", "woeplanet:8.0.0"], "meta:indexed": "2020-08-20T20:56:18.497958", "meta:updated": "2020-08-22T03:00:14.920955", "woe:alias_SPA_S": ["Estacion de Cuatro Vientos", "Estacion del Cuatro Vientos", "Estacion Cuatro Vientos"], "woe:alias_SPA_V": ["Estaci\u00f3n Cuatro Vientos", "Estaci\u00f3n del Cuatro Vientos"], "woe:hierarchy": {"continent": 24865675, "country": 23424950, "town": 0, "planet": 1, "county": 12602090, "suburb": 0, "state": 12578024, "region": 0, "localadmin": 12688024}, "woe:timezone_id": 56043644, "woe:hash": "ezjm9wx4uk7h", "woe:centroid": [-3.79147, 40.377998], "geom:latitude": 40.377998, "geom:longitude": -3.79147, "geom:hash": "ezjm9wx4uk7h", "woe:latitude": 40.377998, "geom:centroid": [-3.79147, 40.377998], "woe:longitude": -3.79147, "woe:repo": "woeplanet-poi-es"}, "geometry": {"coordinates": [-3.79147, 40.377998], "type": "Point"}}