{"type": "Feature", "id": 23238415, "properties": {"woe:id": 23238415, "woe:parent_id": 753330, "woe:name": "Museo Monasterio de la Encarnaci\u00f3n", "woe:placetype": 20, "woe:placetype_name": "POI", "woe:lang": "SPA", "iso:country": "ES", "meta:provider": ["geoplanet:7.3.1", "geoplanet:7.3.2", "geoplanet:7.4.0", "geoplanet:7.4.1", "geoplanet:7.5.1", "geoplanet:7.5.2", "geoplanet:7.6.0", "geoplanet:7.8.1", "geoplanet:7.9.0", "geoplanet:7.10.0", "geoplanet:8.0.0", "woeplanet:8.0.0"], "meta:indexed": "2020-08-20T20:56:18.819374", "meta:updated": "2020-08-22T03:00:15.040455", "woe:alias_SPA_S": ["Museo Monasterio de la Encarnacion"], "woe:hierarchy": {"continent": 24865675, "country": 23424950, "town": 0, "planet": 1, "county": 12602115, "suburb": 0, "state": 12578033, "region": 0, "localadmin": 12691140}, "woe:timezone_id": 56043644, "woe:hash": "ezhxm46ufr7b", "woe:centroid": [-4.69827, 40.662628], "geom:latitude": 40.662628, "geom:longitude": -4.69827, "geom:hash": "ezhxm46ufr7b", "woe:latitude": 40.662628, "geom:centroid": [-4.69827, 40.662628], "woe:longitude": -4.69827, "woe:repo": "woeplanet-poi-es"}, "geometry": {"coordinates": [-4.69827, 40.662628], "type": "Point"}}