{"type": "Feature", "id": 23266009, "properties": {"woe:id": 23266009, "woe:parent_id": 775249, "woe:name": "Estaci\u00f3n de Nord Terrassa", "woe:placetype": 20, "woe:placetype_name": "POI", "woe:lang": "UNK", "iso:country": "ES", "meta:provider": ["geoplanet:7.3.1", "geoplanet:7.3.2", "geoplanet:7.4.0", "geoplanet:7.4.1", "geoplanet:7.5.1", "geoplanet:7.5.2", "geoplanet:7.6.0", "geoplanet:7.8.1", "geoplanet:7.9.0", "geoplanet:7.10.0", "geoplanet:8.0.0", "woeplanet:8.0.0"], "meta:indexed": "2020-08-20T20:56:19.309533", "woe:alias_UNK_V": ["Estaci\u00f3n Nord Terrassa", "Estaci\u00f3n del Nord Terrassa"], "woe:alias_UNK_S": ["Estacion de Nord Terrassa", "Estacion del Nord Terrassa", "Estacion Nord Terrassa"], "meta:updated": "2020-08-22T03:00:15.211534", "woe:hierarchy": {"continent": 24865675, "country": 23424950, "town": 0, "planet": 1, "county": 12602124, "suburb": 0, "state": 12578034, "region": 0, "localadmin": 12693655}, "woe:timezone_id": 56043644, "woe:hash": "sp3kmzdsphq5", "woe:centroid": [2.01424, 41.570229], "geom:latitude": 41.570229, "geom:longitude": 2.01424, "geom:hash": "sp3kmzdsphq5", "woe:latitude": 41.570229, "geom:centroid": [2.01424, 41.570229], "woe:longitude": 2.01424, "woe:repo": "woeplanet-poi-es"}, "geometry": {"coordinates": [2.01424, 41.570229], "type": "Point"}}