{"type": "Feature", "id": 23284460, "properties": {"woe:id": 23284460, "woe:parent_id": 752318, "woe:name": "Centro Cultural de San Gin\u00e9s", "woe:placetype": 20, "woe:placetype_name": "POI", "woe:lang": "SPA", "iso:country": "ES", "meta:provider": ["geoplanet:7.3.1", "geoplanet:7.3.2", "geoplanet:7.4.0", "geoplanet:7.4.1", "geoplanet:7.5.1", "geoplanet:7.5.2", "geoplanet:7.6.0", "geoplanet:7.8.1", "geoplanet:7.9.0", "geoplanet:7.10.0", "geoplanet:8.0.0", "woeplanet:8.0.0"], "meta:indexed": "2020-08-20T20:56:19.595721", "meta:updated": "2020-08-22T03:00:15.323081", "woe:alias_SPA_S": ["Centro Cultural de San Gines"], "woe:hierarchy": {"continent": 24865675, "country": 23424950, "town": 0, "planet": 1, "county": 12602091, "suburb": 0, "state": 12578025, "region": 0, "localadmin": 12688141}, "woe:timezone_id": 56043644, "woe:hash": "eyxmg0kxu4r8", "woe:centroid": [-0.91649, 37.575958], "geom:latitude": 37.575958, "geom:longitude": -0.91649, "geom:hash": "eyxmg0kxu4r8", "woe:latitude": 37.575958, "geom:centroid": [-0.91649, 37.575958], "woe:longitude": -0.91649, "woe:repo": "woeplanet-poi-es"}, "geometry": {"coordinates": [-0.91649, 37.575958], "type": "Point"}}