{"type": "Feature", "id": 56060760, "geometry": {"type": "Point", "coordinates": [2.18682, 41.38496]}, "properties": {"woe:id": 56060760, "woe:parent_id": 753693, "woe:name": "Univ. Pompeu Fabra-Estaci\u00f3 Fran\u00e7a", "woe:placetype": 20, "woe:placetype_name": "POI", "woe:lang": "UNK", "iso:country": "ES", "meta:provider": ["geoplanet:7.3.1", "geoplanet:7.3.2", "geoplanet:7.4.0", "geoplanet:7.4.1", "geoplanet:7.5.1", "geoplanet:7.5.2", "geoplanet:7.6.0", "geoplanet:7.8.1", "geoplanet:7.9.0", "geoplanet:7.10.0", "geoplanet:8.0.0", "woeplanet:8.0.0"], "meta:indexed": "2020-08-20T20:56:20.090350", "woe:alias_UNK_V": ["Univ. Pompeu Fabra-Estacio Franca"], "meta:updated": "2020-10-14T11:28:19.464094", "woe:hierarchy": {"continent": 24865675, "country": 23424950, "town": 0, "planet": 1, "county": 12602124, "suburb": 0, "state": 12578034, "region": 0, "localadmin": 12693396}, "woe:timezone_id": 56043644, "woe:hash": "sp3e3vbkueen", "woe:centroid": [2.18682, 41.38496], "geom:latitude": 41.38496, "geom:longitude": 2.18682, "geom:hash": "sp3e3vbkueen", "woe:latitude": 41.38496, "geom:centroid": [2.18682, 41.38496], "woe:longitude": 2.18682, "woe:repo": "woeplanet-poi-es", "geom:area": 0.0, "woe:scale": 19}}