{"type": "Feature", "id": 23264103, "geometry": {"type": "Point", "coordinates": [2.00285, 41.435478]}, "properties": {"woe:id": 23264103, "woe:parent_id": 769391, "woe:name": "Estaci\u00f3n de Papiol", "woe:placetype": 20, "woe:placetype_name": "POI", "woe:lang": "UNK", "iso:country": "ES", "meta:provider": ["geoplanet:7.3.1", "geoplanet:7.3.2", "geoplanet:7.4.0", "geoplanet:7.4.1", "geoplanet:7.5.1", "geoplanet:7.5.2", "geoplanet:7.6.0", "geoplanet:7.8.1", "geoplanet:7.9.0", "geoplanet:7.10.0", "geoplanet:8.0.0", "woeplanet:8.0.0"], "meta:indexed": "2020-08-20T20:56:19.254396", "woe:alias_UNK_V": ["Estaci\u00f3n Papiol", "Estaci\u00f3n del Papiol"], "woe:alias_UNK_S": ["Estacion de Papiol", "Estacion del Papiol", "Estacion Papiol"], "meta:updated": "2020-10-14T11:28:15.486943", "woe:hierarchy": {"continent": 24865675, "country": 23424950, "town": 0, "planet": 1, "county": 12602124, "suburb": 0, "state": 12578034, "region": 0, "localadmin": 12693538}, "woe:timezone_id": 56043644, "woe:hash": "sp37tx47jucn", "woe:centroid": [2.00285, 41.435478], "geom:latitude": 41.435478, "geom:longitude": 2.00285, "geom:hash": "sp37tx47jucn", "woe:latitude": 41.435478, "geom:centroid": [2.00285, 41.435478], "woe:longitude": 2.00285, "woe:repo": "woeplanet-poi-es", "geom:area": 0.0, "woe:scale": 19}}