{"type": "Feature", "id": 56060719, "geometry": {"type": "Point", "coordinates": [-3.87368, 40.335159]}, "properties": {"woe:id": 56060719, "woe:parent_id": 767893, "woe:name": "Universidad Rey Juan Carlos", "woe:placetype": 20, "woe:placetype_name": "POI", "woe:lang": "SPA", "iso:country": "ES", "meta:provider": ["geoplanet:7.3.1", "geoplanet:7.3.2", "geoplanet:7.4.0", "geoplanet:7.4.1", "geoplanet:7.5.1", "geoplanet:7.5.2", "geoplanet:7.6.0", "geoplanet:7.8.1", "geoplanet:7.9.0", "geoplanet:7.10.0", "geoplanet:8.0.0", "woeplanet:8.0.0"], "meta:indexed": "2020-08-20T20:56:20.061232", "meta:updated": "2020-10-14T11:28:19.427972", "woe:hierarchy": {"continent": 24865675, "country": 23424950, "town": 0, "planet": 1, "county": 12602090, "suburb": 0, "state": 12578024, "region": 0, "localadmin": 12688036}, "woe:timezone_id": 56043644, "woe:hash": "ezjjryg32dwg", "woe:centroid": [-3.87368, 40.335159], "geom:latitude": 40.335159, "geom:longitude": -3.87368, "geom:hash": "ezjjryg32dwg", "woe:latitude": 40.335159, "geom:centroid": [-3.87368, 40.335159], "woe:longitude": -3.87368, "woe:repo": "woeplanet-poi-es", "geom:area": 0.0, "woe:scale": 19}}