{"type": "Feature", "id": 23262073, "geometry": {"type": "Point", "coordinates": [1.85499, 41.64085]}, "properties": {"woe:id": 23262073, "woe:parent_id": 20222453, "woe:name": "Estaci\u00f3n de Castellbell I Villar", "woe:placetype": 20, "woe:placetype_name": "POI", "woe:lang": "UNK", "iso:country": "ES", "meta:provider": ["geoplanet:7.3.1", "geoplanet:7.3.2", "geoplanet:7.4.0", "geoplanet:7.4.1", "geoplanet:7.5.1", "geoplanet:7.5.2", "geoplanet:7.6.0", "geoplanet:7.8.1", "geoplanet:7.9.0", "geoplanet:7.10.0", "geoplanet:8.0.0", "woeplanet:8.0.0"], "meta:indexed": "2020-08-20T20:56:19.191576", "woe:alias_UNK_V": ["Estaci\u00f3n Castellbell I Villar", "Estaci\u00f3n del Castellbell I Villar"], "woe:alias_UNK_S": ["Estacion de Castellbell I Villar", "Estacion del Castellbell I Villar", "Estacion Castellbell I Villar"], "meta:updated": "2020-10-14T11:28:15.850540", "woe:hierarchy": {"continent": 24865675, "country": 23424950, "town": 0, "planet": 1, "county": 12602124, "suburb": 0, "state": 12578034, "region": 0, "localadmin": 12693431}, "woe:timezone_id": 56043644, "woe:hash": "sp3kfhqz83hc", "woe:centroid": [1.85499, 41.64085], "geom:latitude": 41.64085, "geom:longitude": 1.85499, "geom:hash": "sp3kfhqz83hc", "woe:latitude": 41.64085, "geom:centroid": [1.85499, 41.64085], "woe:longitude": 1.85499, "woe:repo": "woeplanet-poi-es", "geom:area": 0.0, "woe:scale": 19}}