{"type": "Feature", "id": 23248706, "properties": {"woe:id": 23248706, "woe:parent_id": 777341, "woe:name": "Estaci\u00f3n de Vigo", "woe:placetype": 20, "woe:placetype_name": "POI", "woe:lang": "SPA", "iso:country": "ES", "meta:provider": ["geoplanet:7.3.1", "geoplanet:7.3.2", "geoplanet:7.4.0", "geoplanet:7.4.1", "geoplanet:7.5.1", "geoplanet:7.5.2", "geoplanet:7.6.0", "geoplanet:7.8.1", "geoplanet:7.9.0", "geoplanet:7.10.0", "geoplanet:8.0.0", "woeplanet:8.0.0"], "meta:indexed": "2020-08-20T20:56:18.926281", "meta:updated": "2020-08-22T03:00:15.079373", "woe:alias_SPA_S": ["Estacion de Vigo", "Estacion del Vigo", "Estacion Vigo"], "woe:alias_SPA_V": ["Estaci\u00f3n Vigo", "Estaci\u00f3n del Vigo"], "woe:hierarchy": {"continent": 24865675, "country": 23424950, "town": 0, "planet": 1, "county": 12602133, "suburb": 0, "state": 12578036, "region": 0, "localadmin": 12695011}, "woe:timezone_id": 56043644, "woe:hash": "ez9b38qqz8ph", "woe:centroid": [-8.71423, 42.233978], "geom:latitude": 42.233978, "geom:longitude": -8.71423, "geom:hash": "ez9b38qqz8ph", "woe:latitude": 42.233978, "geom:centroid": [-8.71423, 42.233978], "woe:longitude": -8.71423, "woe:repo": "woeplanet-poi-es"}, "geometry": {"coordinates": [-8.71423, 42.233978], "type": "Point"}}