{"type": "Feature", "id": 23224253, "geometry": {"type": "Point", "coordinates": [-6.37092, 39.474899]}, "properties": {"woe:id": 23224253, "woe:parent_id": 755379, "woe:name": "Arco de la Estrella", "woe:placetype": 20, "woe:placetype_name": "POI", "woe:lang": "SPA", "iso:country": "ES", "meta:provider": ["geoplanet:7.3.1", "geoplanet:7.3.2", "geoplanet:7.4.0", "geoplanet:7.4.1", "geoplanet:7.5.1", "geoplanet:7.5.2", "geoplanet:7.6.0", "geoplanet:7.8.1", "geoplanet:7.9.0", "geoplanet:7.10.0", "geoplanet:8.0.0", "woeplanet:8.0.0"], "meta:indexed": "2020-08-20T20:56:18.634032", "meta:updated": "2020-10-14T11:28:15.496463", "woe:hierarchy": {"continent": 24865675, "country": 23424950, "town": 0, "planet": 1, "county": 12602129, "suburb": 0, "state": 12578035, "region": 0, "localadmin": 12694519}, "woe:timezone_id": 56043644, "woe:hash": "ez52x40vfy98", "woe:centroid": [-6.37092, 39.474899], "geom:latitude": 39.474899, "geom:longitude": -6.37092, "geom:hash": "ez52x40vfy98", "woe:latitude": 39.474899, "geom:centroid": [-6.37092, 39.474899], "woe:longitude": -6.37092, "woe:repo": "woeplanet-poi-es", "geom:area": 0.0, "woe:scale": 19}}