{"type": "Feature", "id": 23251463, "geometry": {"type": "Point", "coordinates": [-4.11766, 40.946239]}, "properties": {"woe:id": 23251463, "woe:parent_id": 774288, "woe:name": "Museo de la Academia de Artiller\u00eda de Segovia", "woe:placetype": 20, "woe:placetype_name": "POI", "woe:lang": "SPA", "iso:country": "ES", "meta:provider": ["geoplanet:7.3.1", "geoplanet:7.3.2", "geoplanet:7.4.0", "geoplanet:7.4.1", "geoplanet:7.5.1", "geoplanet:7.5.2", "geoplanet:7.6.0", "geoplanet:7.8.1", "geoplanet:7.9.0", "geoplanet:7.10.0", "geoplanet:8.0.0", "woeplanet:8.0.0"], "meta:indexed": "2020-08-20T20:56:18.966797", "meta:updated": "2020-10-14T11:28:15.937923", "woe:alias_SPA_S": ["Museo de la Academia de Artilleria de Segovia"], "woe:hierarchy": {"continent": 24865675, "country": 23424950, "town": 0, "planet": 1, "county": 12602120, "suburb": 0, "state": 12578033, "region": 0, "localadmin": 12692685}, "woe:timezone_id": 56043644, "woe:hash": "ezm0fq195s4j", "woe:centroid": [-4.11766, 40.946239], "geom:latitude": 40.946239, "geom:longitude": -4.11766, "geom:hash": "ezm0fq195s4j", "woe:latitude": 40.946239, "geom:centroid": [-4.11766, 40.946239], "woe:longitude": -4.11766, "woe:repo": "woeplanet-poi-es", "geom:area": 0.0, "woe:scale": 19}}