{"type": "Feature", "id": 56060804, "geometry": {"type": "Point", "coordinates": [-6.92061, 37.26685]}, "properties": {"woe:id": 56060804, "woe:parent_id": 762399, "woe:name": "Campus Universitario El Carmen", "woe:placetype": 20, "woe:placetype_name": "POI", "woe:lang": "SPA", "iso:country": "ES", "meta:provider": ["geoplanet:7.3.1", "geoplanet:7.3.2", "geoplanet:7.4.0", "geoplanet:7.4.1", "geoplanet:7.5.1", "geoplanet:7.5.2", "geoplanet:7.6.0", "geoplanet:7.8.1", "geoplanet:7.9.0", "geoplanet:7.10.0", "geoplanet:8.0.0", "woeplanet:8.0.0"], "meta:indexed": "2020-08-20T20:56:20.122448", "meta:updated": "2020-10-14T11:28:19.374069", "woe:hierarchy": {"continent": 24865675, "country": 23424950, "town": 0, "planet": 1, "county": 12602100, "suburb": 0, "state": 12578029, "region": 0, "localadmin": 12689055}, "woe:timezone_id": 56043644, "woe:hash": "eyeh480x4h75", "woe:centroid": [-6.92061, 37.26685], "geom:latitude": 37.26685, "geom:longitude": -6.92061, "geom:hash": "eyeh480x4h75", "woe:latitude": 37.26685, "geom:centroid": [-6.92061, 37.26685], "woe:longitude": -6.92061, "woe:repo": "woeplanet-poi-es", "geom:area": 0.0, "woe:scale": 19}}