{"type": "Feature", "id": 23253517, "properties": {"woe:id": 23253517, "woe:parent_id": 20220047, "woe:name": "Estaci\u00f3n de Feve Unibertsitatea", "woe:placetype": 20, "woe:placetype_name": "POI", "woe:lang": "SPA", "iso:country": "ES", "meta:provider": ["geoplanet:7.3.1", "geoplanet:7.3.2", "geoplanet:7.4.0", "geoplanet:7.4.1", "geoplanet:7.5.1", "geoplanet:7.5.2", "geoplanet:7.6.0", "geoplanet:7.8.1", "geoplanet:7.9.0", "geoplanet:7.10.0", "geoplanet:8.0.0", "woeplanet:8.0.0"], "meta:indexed": "2020-08-20T20:56:19.001773", "meta:updated": "2020-08-22T03:00:15.107641", "woe:alias_SPA_S": ["Estacion de Feve Unibertsitatea", "Estacion del Feve Unibertsitatea", "Estacion Feve Unibertsitatea"], "woe:alias_SPA_V": ["Estaci\u00f3n Feve Unibertsitatea", "Estaci\u00f3n del Feve Unibertsitatea"], "woe:hierarchy": {"continent": 24865675, "country": 23424950, "town": 0, "planet": 1, "county": 12602136, "suburb": 0, "state": 12578037, "region": 0, "localadmin": 12695182}, "woe:timezone_id": 56043644, "woe:hash": "eztyjjd22qgv", "woe:centroid": [-2.94123, 43.27248], "geom:latitude": 43.27248, "geom:longitude": -2.94123, "geom:hash": "eztyjjd22qgv", "woe:latitude": 43.27248, "geom:centroid": [-2.94123, 43.27248], "woe:longitude": -2.94123, "woe:repo": "woeplanet-poi-es"}, "geometry": {"coordinates": [-2.94123, 43.27248], "type": "Point"}}