{"type": "Feature", "id": 23269457, "geometry": {"type": "Point", "coordinates": [-0.55113, 42.571171]}, "properties": {"woe:id": 23269457, "woe:parent_id": 762756, "woe:name": "Ciudadela de Jaca", "woe:placetype": 20, "woe:placetype_name": "POI", "woe:lang": "SPA", "iso:country": "ES", "meta:provider": ["geoplanet:7.3.1", "geoplanet:7.3.2", "geoplanet:7.4.0", "geoplanet:7.4.1", "geoplanet:7.5.1", "geoplanet:7.5.2", "geoplanet:7.6.0", "geoplanet:7.8.1", "geoplanet:7.9.0", "geoplanet:7.10.0", "geoplanet:8.0.0", "woeplanet:8.0.0"], "meta:indexed": "2020-08-20T20:56:19.368686", "meta:updated": "2020-10-14T11:28:15.425296", "woe:hierarchy": {"continent": 24865675, "country": 23424950, "town": 0, "planet": 1, "county": 12602105, "suburb": 0, "state": 12578030, "region": 0, "localadmin": 12689501}, "woe:timezone_id": 56043644, "woe:hash": "ezxd5myej9rw", "woe:centroid": [-0.55113, 42.571171], "geom:latitude": 42.571171, "geom:longitude": -0.55113, "geom:hash": "ezxd5myej9rw", "woe:latitude": 42.571171, "geom:centroid": [-0.55113, 42.571171], "woe:longitude": -0.55113, "woe:repo": "woeplanet-poi-es", "geom:area": 0.0, "woe:scale": 19}}