{"type": "Feature", "id": 23263960, "geometry": {"type": "Point", "coordinates": [1.85055, 41.608212]}, "properties": {"woe:id": 23263960, "woe:parent_id": 767470, "woe:name": "Estaci\u00f3n de Monistrol de Montserrat", "woe:placetype": 20, "woe:placetype_name": "POI", "woe:lang": "UNK", "iso:country": "ES", "meta:provider": ["geoplanet:7.3.1", "geoplanet:7.3.2", "geoplanet:7.4.0", "geoplanet:7.4.1", "geoplanet:7.5.1", "geoplanet:7.5.2", "geoplanet:7.6.0", "geoplanet:7.8.1", "geoplanet:7.9.0", "geoplanet:7.10.0", "geoplanet:8.0.0", "woeplanet:8.0.0"], "meta:indexed": "2020-08-20T20:56:19.248979", "woe:alias_UNK_V": ["Fgc-Monistrol de Montserrat", "Estaci\u00f3n Monistrol de Montserrat", "Estaci\u00f3n del Monistrol de Montserrat"], "woe:alias_UNK_S": ["Estacion de Monistrol de Montserrat", "Estacion del Monistrol de Montserrat", "Estacion Monistrol de Montserrat"], "meta:updated": "2020-10-14T11:28:15.876993", "woe:hierarchy": {"continent": 24865675, "country": 23424950, "town": 0, "planet": 1, "county": 12602124, "suburb": 0, "state": 12578034, "region": 0, "localadmin": 12693508}, "woe:timezone_id": 56043644, "woe:hash": "sp3kdne92uyh", "woe:centroid": [1.85055, 41.608212], "geom:latitude": 41.608212, "geom:longitude": 1.85055, "geom:hash": "sp3kdne92uyh", "woe:latitude": 41.608212, "geom:centroid": [1.85055, 41.608212], "woe:longitude": 1.85055, "woe:repo": "woeplanet-poi-es", "geom:area": 0.0, "woe:scale": 19}}