{"type": "Feature", "id": 23234392, "geometry": {"type": "Point", "coordinates": [-5.62425, 37.477692]}, "properties": {"woe:id": 23234392, "woe:parent_id": 756224, "woe:name": "Restos de la V\u00eda Augusta y Puente", "woe:placetype": 20, "woe:placetype_name": "POI", "woe:lang": "SPA", "iso:country": "ES", "meta:provider": ["geoplanet:7.3.1", "geoplanet:7.3.2", "geoplanet:7.4.0", "geoplanet:7.4.1", "geoplanet:7.5.1", "geoplanet:7.5.2", "geoplanet:7.6.0", "geoplanet:7.8.1", "geoplanet:7.9.0", "geoplanet:7.10.0", "geoplanet:8.0.0", "woeplanet:8.0.0"], "meta:indexed": "2020-08-20T20:56:18.776368", "meta:updated": "2020-10-14T11:28:15.530776", "woe:alias_SPA_S": ["Restos de la Via Augusta y Puente"], "woe:hierarchy": {"continent": 24865675, "country": 23424950, "town": 0, "planet": 1, "county": 12602104, "suburb": 0, "state": 12578029, "region": 0, "localadmin": 12689315}, "woe:timezone_id": 56043644, "woe:hash": "eysj0n8e3kph", "woe:centroid": [-5.62425, 37.477692], "geom:latitude": 37.477692, "geom:longitude": -5.62425, "geom:hash": "eysj0n8e3kph", "woe:latitude": 37.477692, "geom:centroid": [-5.62425, 37.477692], "woe:longitude": -5.62425, "woe:repo": "woeplanet-poi-es", "geom:area": 0.0, "woe:scale": 19}}