{"type": "Feature", "id": 23229817, "geometry": {"type": "Point", "coordinates": [-3.58548, 37.119511]}, "properties": {"woe:id": 23229817, "woe:parent_id": 779150, "woe:name": "Ba\u00f1os \u00c1rabes de la Zubia", "woe:placetype": 20, "woe:placetype_name": "POI", "woe:lang": "SPA", "iso:country": "ES", "meta:provider": ["geoplanet:7.3.1", "geoplanet:7.3.2", "geoplanet:7.4.0", "geoplanet:7.4.1", "geoplanet:7.5.1", "geoplanet:7.5.2", "geoplanet:7.6.0", "geoplanet:7.8.1", "geoplanet:7.9.0", "geoplanet:7.10.0", "geoplanet:8.0.0", "woeplanet:8.0.0"], "meta:indexed": "2020-08-20T20:56:18.696257", "meta:updated": "2020-10-14T11:28:15.556912", "woe:alias_SPA_S": ["Banos Arabes de la Zubia", "Banyos Arabes de la Zubia"], "woe:hierarchy": {"continent": 24865675, "country": 23424950, "town": 0, "planet": 1, "county": 12602099, "suburb": 0, "state": 12578029, "region": 0, "localadmin": 12689013}, "woe:timezone_id": 56043644, "woe:hash": "eyt7nmmhu62k", "woe:centroid": [-3.58548, 37.119511], "geom:latitude": 37.119511, "geom:longitude": -3.58548, "geom:hash": "eyt7nmmhu62k", "woe:latitude": 37.119511, "geom:centroid": [-3.58548, 37.119511], "woe:longitude": -3.58548, "woe:repo": "woeplanet-poi-es", "geom:area": 0.0, "woe:scale": 19}}