{"type": "Feature", "id": 22410763, "properties": {"woe:id": 22410763, "woe:parent_id": 755404, "woe:name": "Estadio Ram\u00f3n de Carranza", "woe:placetype": 20, "woe:placetype_name": "POI", "woe:lang": "SPA", "iso:country": "ES", "meta:provider": ["geoplanet:7.3.1", "geoplanet:7.3.2", "geoplanet:7.4.0", "geoplanet:7.4.1", "geoplanet:7.5.1", "geoplanet:7.5.2", "geoplanet:7.6.0", "geoplanet:7.8.1", "geoplanet:7.9.0", "geoplanet:7.10.0", "geoplanet:8.0.0", "woeplanet:8.0.0"], "meta:indexed": "2020-08-20T20:56:18.449422", "meta:updated": "2020-08-22T03:00:14.903285", "woe:alias_SPA_S": ["Estadio Ramon de Carranza"], "woe:hierarchy": {"continent": 24865675, "country": 23424950, "town": 0, "planet": 1, "county": 12602096, "suburb": 0, "state": 12578029, "region": 0, "localadmin": 12688739}, "woe:timezone_id": 56043644, "woe:hash": "ey7x9jp9wgpx", "woe:centroid": [-6.27358, 36.50235], "geom:latitude": 36.50235, "geom:longitude": -6.27358, "geom:hash": "ey7x9jp9wgpx", "woe:latitude": 36.50235, "geom:centroid": [-6.27358, 36.50235], "woe:longitude": -6.27358, "woe:repo": "woeplanet-poi-es"}, "geometry": {"coordinates": [-6.27358, 36.50235], "type": "Point"}}