{"type": "Feature", "id": 23224257, "geometry": {"type": "Point", "coordinates": [-6.37079, 39.47345]}, "properties": {"woe:id": 23224257, "woe:parent_id": 755379, "woe:name": "Casa de Sol\u00eds o del Sol", "woe:placetype": 20, "woe:placetype_name": "POI", "woe:lang": "SPA", "iso:country": "ES", "meta:provider": ["geoplanet:7.3.1", "geoplanet:7.3.2", "geoplanet:7.4.0", "geoplanet:7.4.1", "geoplanet:7.5.1", "geoplanet:7.5.2", "geoplanet:7.6.0", "geoplanet:7.8.1", "geoplanet:7.9.0", "geoplanet:7.10.0", "geoplanet:8.0.0", "woeplanet:8.0.0"], "meta:indexed": "2020-08-20T20:56:18.634881", "meta:updated": "2020-10-14T11:28:15.498145", "woe:alias_SPA_S": ["Casa de Solis o del Sol"], "woe:hierarchy": {"continent": 24865675, "country": 23424950, "town": 0, "planet": 1, "county": 12602129, "suburb": 0, "state": 12578035, "region": 0, "localadmin": 12694519}, "woe:timezone_id": 56043644, "woe:hash": "ez52x1bvtb6t", "woe:centroid": [-6.37079, 39.47345], "geom:latitude": 39.47345, "geom:longitude": -6.37079, "geom:hash": "ez52x1bvtb6t", "woe:latitude": 39.47345, "geom:centroid": [-6.37079, 39.47345], "woe:longitude": -6.37079, "woe:repo": "woeplanet-poi-es", "geom:area": 0.0, "woe:scale": 19}}