{"type": "Feature", "id": 55863680, "geometry": {"type": "Point", "coordinates": [-3.69869, 40.419449]}, "properties": {"woe:id": 55863680, "woe:parent_id": 20219948, "woe:name": "Gran Via", "woe:placetype": 20, "woe:placetype_name": "POI", "woe:lang": "SPA", "iso:country": "ES", "meta:provider": ["geoplanet:7.3.1", "geoplanet:7.3.2", "geoplanet:7.4.0", "geoplanet:7.4.1", "geoplanet:7.5.1", "geoplanet:7.5.2", "geoplanet:7.6.0", "geoplanet:7.8.1", "geoplanet:7.9.0", "geoplanet:7.10.0", "geoplanet:8.0.0", "woeplanet:8.0.0"], "meta:indexed": "2020-08-20T20:56:20.041185", "meta:updated": "2020-10-14T11:28:15.378657", "woe:hierarchy": {"continent": 24865675, "country": 23424950, "town": 0, "planet": 1, "county": 12602090, "suburb": 0, "state": 12578024, "region": 0, "localadmin": 12688024}, "woe:timezone_id": 56043644, "woe:hash": "ezjmgy4sq72u", "woe:centroid": [-3.69869, 40.419449], "geom:latitude": 40.419449, "geom:longitude": -3.69869, "geom:hash": "ezjmgy4sq72u", "woe:latitude": 40.419449, "geom:centroid": [-3.69869, 40.419449], "woe:longitude": -3.69869, "woe:repo": "woeplanet-poi-es", "geom:area": 0.0, "woe:scale": 19}}