{"type": "Feature", "id": 23271717, "properties": {"woe:id": 23271717, "woe:parent_id": 773536, "woe:name": "Palacio de Los I\u00f1\u00edguez Abarca", "woe:placetype": 20, "woe:placetype_name": "POI", "woe:lang": "SPA", "iso:country": "ES", "meta:provider": ["geoplanet:7.3.1", "geoplanet:7.3.2", "geoplanet:7.4.0", "geoplanet:7.4.1", "geoplanet:7.5.1", "geoplanet:7.5.2", "geoplanet:7.6.0", "geoplanet:7.8.1", "geoplanet:7.9.0", "geoplanet:7.10.0", "geoplanet:8.0.0", "woeplanet:8.0.0"], "meta:indexed": "2020-08-20T20:56:19.414128", "meta:updated": "2020-08-22T03:00:15.250879", "woe:alias_SPA_S": ["Palacio de Los Iniguez Abarca", "Palacio de Los Inyiguez Abarca"], "woe:hierarchy": {"continent": 24865675, "country": 23424950, "town": 0, "planet": 1, "county": 12602092, "suburb": 0, "state": 12578026, "region": 0, "localadmin": 12688397}, "woe:timezone_id": 56043644, "woe:hash": "ezx44ybdut0k", "woe:centroid": [-1.28452, 42.576641], "geom:latitude": 42.576641, "geom:longitude": -1.28452, "geom:hash": "ezx44ybdut0k", "woe:latitude": 42.576641, "geom:centroid": [-1.28452, 42.576641], "woe:longitude": -1.28452, "woe:repo": "woeplanet-poi-es"}, "geometry": {"coordinates": [-1.28452, 42.576641], "type": "Point"}}