{"type": "Feature", "id": 56060846, "geometry": {"type": "Point", "coordinates": [-2.18236, 43.047279]}, "properties": {"woe:id": 56060846, "woe:parent_id": 777711, "woe:name": "Mondrag\u00f3n Unibertsitatea", "woe:placetype": 20, "woe:placetype_name": "POI", "woe:lang": "UNK", "iso:country": "ES", "meta:provider": ["geoplanet:7.3.1", "geoplanet:7.3.2", "geoplanet:7.4.0", "geoplanet:7.4.1", "geoplanet:7.5.1", "geoplanet:7.5.2", "geoplanet:7.6.0", "geoplanet:7.8.1", "geoplanet:7.9.0", "geoplanet:7.10.0", "geoplanet:8.0.0", "woeplanet:8.0.0"], "meta:indexed": "2020-08-20T20:56:20.155621", "woe:alias_UNK_V": ["Mondragon Unibertsitatea"], "meta:updated": "2020-10-14T11:28:19.415586", "woe:alias_SPA_V": ["Universidad de Mondragon", "Universidad de Mondrag\u00f3n"], "woe:hierarchy": {"continent": 24865675, "country": 23424950, "town": 0, "planet": 1, "county": 12602135, "suburb": 0, "state": 12578037, "region": 0, "localadmin": 12695133}, "woe:timezone_id": 56043644, "woe:hash": "ezwkykdbe66m", "woe:centroid": [-2.18236, 43.047279], "geom:latitude": 43.047279, "geom:longitude": -2.18236, "geom:hash": "ezwkykdbe66m", "woe:latitude": 43.047279, "geom:centroid": [-2.18236, 43.047279], "woe:longitude": -2.18236, "woe:repo": "woeplanet-poi-es", "geom:area": 0.0, "woe:scale": 19}}