{"type": "Feature", "id": 56060771, "properties": {"woe:id": 56060771, "woe:parent_id": 775249, "woe:name": "Universitat Oberta de Catalunya", "woe:placetype": 20, "woe:placetype_name": "POI", "woe:lang": "UNK", "iso:country": "ES", "meta:provider": ["geoplanet:7.3.1", "geoplanet:7.3.2", "geoplanet:7.4.0", "geoplanet:7.4.1", "geoplanet:7.5.1", "geoplanet:7.5.2", "geoplanet:7.6.0", "geoplanet:7.8.1", "geoplanet:7.9.0", "geoplanet:7.10.0", "geoplanet:8.0.0", "woeplanet:8.0.0"], "meta:indexed": "2020-08-20T20:56:20.098515", "meta:updated": "2020-08-22T03:00:15.509559", "woe:hierarchy": {"continent": 24865675, "country": 23424950, "town": 0, "planet": 1, "county": 12602124, "suburb": 0, "state": 12578034, "region": 0, "localadmin": 12693655}, "woe:timezone_id": 56043644, "woe:hash": "sp3kmwv72qju", "woe:centroid": [2.00674, 41.56599], "geom:latitude": 41.56599, "geom:longitude": 2.00674, "geom:hash": "sp3kmwv72qju", "woe:latitude": 41.56599, "geom:centroid": [2.00674, 41.56599], "woe:longitude": 2.00674, "woe:repo": "woeplanet-poi-es"}, "geometry": {"coordinates": [2.00674, 41.56599], "type": "Point"}}