{"type": "Feature", "id": 23230693, "properties": {"woe:id": 23230693, "woe:parent_id": 762761, "woe:name": "Est\u00e1dio Municipal la Vict\u00f3ria", "woe:placetype": 20, "woe:placetype_name": "POI", "woe:lang": "SPA", "iso:country": "ES", "meta:provider": ["geoplanet:7.3.1", "geoplanet:7.3.2", "geoplanet:7.4.0", "geoplanet:7.4.1", "geoplanet:7.5.1", "geoplanet:7.5.2", "geoplanet:7.6.0", "geoplanet:7.8.1", "geoplanet:7.9.0", "geoplanet:7.10.0", "geoplanet:8.0.0", "woeplanet:8.0.0"], "meta:indexed": "2020-08-20T20:56:18.712954", "meta:updated": "2020-08-22T03:00:15.003052", "woe:alias_SPA_S": ["Estadio Municipal la Victoria"], "woe:hierarchy": {"continent": 24865675, "country": 23424950, "town": 0, "planet": 1, "county": 12602101, "suburb": 0, "state": 12578029, "region": 0, "localadmin": 12689141}, "woe:timezone_id": 56043644, "woe:hash": "eytqcv43zp64", "woe:centroid": [-3.78689, 37.776829], "geom:latitude": 37.776829, "geom:longitude": -3.78689, "geom:hash": "eytqcv43zp64", "woe:latitude": 37.776829, "geom:centroid": [-3.78689, 37.776829], "woe:longitude": -3.78689, "woe:repo": "woeplanet-poi-es"}, "geometry": {"coordinates": [-3.78689, 37.776829], "type": "Point"}}