{"type": "Feature", "id": 56060856, "geometry": {"type": "Point", "coordinates": [-1.85308, 38.97776]}, "properties": {"woe:id": 56060856, "woe:parent_id": 751648, "woe:name": "Univ. Castilla la Mancha Albacete", "woe:placetype": 20, "woe:placetype_name": "POI", "woe:lang": "SPA", "iso:country": "ES", "meta:provider": ["geoplanet:7.3.1", "geoplanet:7.3.2", "geoplanet:7.4.0", "geoplanet:7.4.1", "geoplanet:7.5.1", "geoplanet:7.5.2", "geoplanet:7.6.0", "geoplanet:7.8.1", "geoplanet:7.9.0", "geoplanet:7.10.0", "geoplanet:8.0.0", "woeplanet:8.0.0"], "meta:indexed": "2020-08-20T20:56:20.162117", "meta:updated": "2020-10-14T11:28:19.407413", "woe:hierarchy": {"continent": 24865675, "country": 23424950, "town": 0, "planet": 1, "county": 12602110, "suburb": 0, "state": 12578032, "region": 0, "localadmin": 12690214}, "woe:timezone_id": 56043644, "woe:hash": "eyyttzdtuj57", "woe:centroid": [-1.85308, 38.97776], "geom:latitude": 38.97776, "geom:longitude": -1.85308, "geom:hash": "eyyttzdtuj57", "woe:latitude": 38.97776, "geom:centroid": [-1.85308, 38.97776], "woe:longitude": -1.85308, "woe:repo": "woeplanet-poi-es", "geom:area": 0.0, "woe:scale": 19}}