{"type": "Feature", "id": 23259452, "properties": {"woe:id": 23259452, "woe:parent_id": 763981, "woe:name": "Estaci\u00f3n de Urquinaona", "woe:placetype": 20, "woe:placetype_name": "POI", "woe:lang": "SPA", "iso:country": "ES", "meta:provider": ["geoplanet:7.3.1", "geoplanet:7.3.2", "geoplanet:7.4.0", "geoplanet:7.4.1", "geoplanet:7.5.1", "geoplanet:7.5.2", "geoplanet:7.6.0", "geoplanet:7.8.1", "geoplanet:7.9.0", "geoplanet:7.10.0", "geoplanet:8.0.0", "woeplanet:8.0.0"], "meta:indexed": "2020-08-20T20:56:19.134000", "meta:updated": "2020-08-22T03:00:15.150668", "woe:alias_SPA_S": ["Estacion de Urquinaona", "Estacion del Urquinaona", "Estacion Urquinaona"], "woe:alias_SPA_V": ["Estaci\u00f3n Urquinaona", "Estaci\u00f3n del Urquinaona"], "woe:hierarchy": {"continent": 24865675, "country": 23424950, "town": 0, "planet": 1, "county": 12602124, "suburb": 0, "state": 12578034, "region": 0, "localadmin": 12693396}, "woe:timezone_id": 56043644, "woe:hash": "sp3e3qwy1qrm", "woe:centroid": [2.17364, 41.389309], "geom:latitude": 41.389309, "geom:longitude": 2.17364, "geom:hash": "sp3e3qwy1qrm", "woe:latitude": 41.389309, "geom:centroid": [2.17364, 41.389309], "woe:longitude": 2.17364, "woe:repo": "woeplanet-poi-es"}, "geometry": {"coordinates": [2.17364, 41.389309], "type": "Point"}}