{"type": "Feature", "id": 23303107, "properties": {"woe:id": 23303107, "woe:parent_id": 20219886, "woe:name": "Real Jard\u00edn Bot\u00e1nico", "woe:placetype": 20, "woe:placetype_name": "POI", "woe:lang": "SPA", "iso:country": "ES", "meta:provider": ["geoplanet:7.3.1", "geoplanet:7.3.2", "geoplanet:7.4.0", "geoplanet:7.4.1", "geoplanet:7.5.1", "geoplanet:7.5.2", "geoplanet:7.6.0", "geoplanet:7.8.1", "geoplanet:7.9.0", "geoplanet:7.10.0", "geoplanet:8.0.0", "woeplanet:8.0.0"], "meta:indexed": "2020-08-20T20:56:19.898098", "meta:updated": "2020-08-22T03:00:15.442045", "woe:alias_SPA_S": ["Real Jardin Botanico"], "woe:alias_SPA_V": ["Realjardinbotanico"], "woe:hierarchy": {"continent": 24865675, "country": 23424950, "town": 0, "planet": 1, "county": 12602090, "suburb": 0, "state": 12578024, "region": 0, "localadmin": 12688024}, "woe:timezone_id": 56043644, "woe:hash": "ezjmguzkn7mz", "woe:centroid": [-3.69216, 40.41254], "geom:latitude": 40.41254, "geom:longitude": -3.69216, "geom:hash": "ezjmguzkn7mz", "woe:latitude": 40.41254, "geom:centroid": [-3.69216, 40.41254], "woe:longitude": -3.69216, "woe:repo": "woeplanet-poi-es"}, "geometry": {"coordinates": [-3.69216, 40.41254], "type": "Point"}}