{"type": "Feature", "id": 23224552, "geometry": {"type": "Point", "coordinates": [-6.55796, 40.135578]}, "properties": {"woe:id": 23224552, "woe:parent_id": 29371021, "woe:name": "Embalse de Borboll\u00f3n", "woe:placetype": 20, "woe:placetype_name": "POI", "woe:lang": "SPA", "iso:country": "ES", "meta:provider": ["geoplanet:7.3.1", "geoplanet:7.3.2", "geoplanet:7.4.0", "geoplanet:7.4.1", "geoplanet:7.5.1", "geoplanet:7.5.2", "geoplanet:7.6.0", "geoplanet:7.8.1", "geoplanet:7.9.0", "geoplanet:7.10.0", "geoplanet:8.0.0", "woeplanet:8.0.0"], "meta:indexed": "2020-08-20T20:56:18.636557", "meta:updated": "2020-10-14T11:28:16.278791", "woe:alias_SPA_S": ["Embalse de Borbollon"], "woe:hierarchy": {"continent": 24865675, "country": 23424950, "town": 0, "planet": 1, "county": 12602129, "suburb": 0, "state": 12578035, "region": 0, "localadmin": 12694653}, "woe:timezone_id": 56043644, "woe:hash": "ez5k6f2wsqn8", "woe:centroid": [-6.55796, 40.135578], "geom:latitude": 40.135578, "geom:longitude": -6.55796, "geom:hash": "ez5k6f2wsqn8", "woe:latitude": 40.135578, "geom:centroid": [-6.55796, 40.135578], "woe:longitude": -6.55796, "woe:repo": "woeplanet-poi-es", "geom:area": 0.0, "woe:scale": 19}}