{"type": "Feature", "id": 23282763, "properties": {"woe:id": 23282763, "woe:parent_id": 756804, "woe:name": "Casino Antiguo", "woe:placetype": 20, "woe:placetype_name": "POI", "woe:lang": "SPA", "iso:country": "ES", "meta:provider": ["geoplanet:7.3.1", "geoplanet:7.3.2", "geoplanet:7.4.0", "geoplanet:7.4.1", "geoplanet:7.5.1", "geoplanet:7.5.2", "geoplanet:7.6.0", "geoplanet:7.8.1", "geoplanet:7.9.0", "geoplanet:7.10.0", "geoplanet:8.0.0", "woeplanet:8.0.0"], "meta:indexed": "2020-08-20T20:56:19.571311", "meta:updated": "2020-08-22T03:00:15.313613", "woe:hierarchy": {"continent": 24865675, "country": 23424950, "town": 0, "planet": 1, "county": 12602138, "suburb": 0, "state": 12578038, "region": 0, "localadmin": 12695443}, "woe:timezone_id": 56043644, "woe:hash": "ezpgrngws5jr", "woe:centroid": [-0.03896, 39.984501], "geom:latitude": 39.984501, "geom:longitude": -0.03896, "geom:hash": "ezpgrngws5jr", "woe:latitude": 39.984501, "geom:centroid": [-0.03896, 39.984501], "woe:longitude": -0.03896, "woe:repo": "woeplanet-poi-es"}, "geometry": {"coordinates": [-0.03896, 39.984501], "type": "Point"}}