{"type": "Feature", "id": 23262559, "properties": {"woe:id": 23262559, "woe:parent_id": 761807, "woe:name": "Estaci\u00f3n de Granollers Centre", "woe:placetype": 20, "woe:placetype_name": "POI", "woe:lang": "UNK", "iso:country": "ES", "meta:provider": ["geoplanet:7.3.1", "geoplanet:7.3.2", "geoplanet:7.4.0", "geoplanet:7.4.1", "geoplanet:7.5.1", "geoplanet:7.5.2", "geoplanet:7.6.0", "geoplanet:7.8.1", "geoplanet:7.9.0", "geoplanet:7.10.0", "geoplanet:8.0.0", "woeplanet:8.0.0"], "meta:indexed": "2020-08-20T20:56:19.207488", "woe:alias_UNK_V": ["Rodalies-Granollers Centre", "Estaci\u00f3n Granollers Centre", "Estaci\u00f3n del Granollers Centre"], "woe:alias_UNK_S": ["Estacion de Granollers Centre", "Estacion del Granollers Centre", "Estacion Granollers Centre"], "meta:updated": "2020-08-22T03:00:15.174098", "woe:hierarchy": {"continent": 24865675, "country": 23424950, "town": 0, "planet": 1, "county": 12602124, "suburb": 0, "state": 12578034, "region": 0, "localadmin": 12693476}, "woe:timezone_id": 56043644, "woe:hash": "sp3ssjh2136t", "woe:centroid": [2.29105, 41.599739], "geom:latitude": 41.599739, "geom:longitude": 2.29105, "geom:hash": "sp3ssjh2136t", "woe:latitude": 41.599739, "geom:centroid": [2.29105, 41.599739], "woe:longitude": 2.29105, "woe:repo": "woeplanet-poi-es"}, "geometry": {"coordinates": [2.29105, 41.599739], "type": "Point"}}