{"type": "Feature", "id": 23271132, "geometry": {"type": "Point", "coordinates": [-1.65002, 42.816471]}, "properties": {"woe:id": 23271132, "woe:parent_id": 769330, "woe:name": "Parque de la Taconera", "woe:placetype": 20, "woe:placetype_name": "POI", "woe:lang": "SPA", "iso:country": "ES", "meta:provider": ["geoplanet:7.3.1", "geoplanet:7.3.2", "geoplanet:7.4.0", "geoplanet:7.4.1", "geoplanet:7.5.1", "geoplanet:7.5.2", "geoplanet:7.6.0", "geoplanet:7.8.1", "geoplanet:7.9.0", "geoplanet:7.10.0", "geoplanet:8.0.0", "woeplanet:8.0.0"], "meta:indexed": "2020-08-20T20:56:19.408263", "meta:updated": "2020-10-14T11:28:15.791317", "woe:hierarchy": {"continent": 24865675, "country": 23424950, "town": 0, "planet": 1, "county": 12602092, "suburb": 0, "state": 12578026, "region": 0, "localadmin": 12688382}, "woe:timezone_id": 56043644, "woe:hash": "ezwgd6w2p8xy", "woe:centroid": [-1.65002, 42.816471], "geom:latitude": 42.816471, "geom:longitude": -1.65002, "geom:hash": "ezwgd6w2p8xy", "woe:latitude": 42.816471, "geom:centroid": [-1.65002, 42.816471], "woe:longitude": -1.65002, "woe:repo": "woeplanet-poi-es", "geom:area": 0.0, "woe:scale": 19}}