{"type": "Feature", "id": 23228123, "geometry": {"type": "Point", "coordinates": [-4.40884, 37.3923]}, "properties": {"woe:id": 23228123, "woe:parent_id": 20224199, "woe:name": "Granadilla", "woe:placetype": 20, "woe:placetype_name": "POI", "woe:lang": "SPA", "iso:country": "ES", "meta:provider": ["geoplanet:7.3.1", "geoplanet:7.3.2", "geoplanet:7.4.0", "geoplanet:7.4.1", "geoplanet:7.5.1", "geoplanet:7.5.2", "geoplanet:7.6.0", "geoplanet:7.8.1", "geoplanet:7.9.0", "geoplanet:7.10.0", "geoplanet:8.0.0", "woeplanet:8.0.0"], "meta:indexed": "2020-08-20T20:56:18.669350", "meta:updated": "2020-10-14T11:28:15.887158", "woe:hierarchy": {"continent": 24865675, "country": 23424950, "town": 0, "planet": 1, "county": 12602098, "suburb": 0, "state": 12578029, "region": 0, "localadmin": 12688829}, "woe:timezone_id": 56043644, "woe:hash": "eysuexj9ftft", "woe:centroid": [-4.40884, 37.3923], "geom:latitude": 37.3923, "geom:longitude": -4.40884, "geom:hash": "eysuexj9ftft", "woe:latitude": 37.3923, "geom:centroid": [-4.40884, 37.3923], "woe:longitude": -4.40884, "woe:repo": "woeplanet-poi-es", "geom:area": 0.0, "woe:scale": 19}}