{"type": "Feature", "id": 23287616, "geometry": {"type": "Point", "coordinates": [-0.53634, 39.56234]}, "properties": {"woe:id": 23287616, "woe:parent_id": 29370054, "woe:name": "Estaci\u00f3n de L'eliana", "woe:placetype": 20, "woe:placetype_name": "POI", "woe:lang": "UNK", "iso:country": "ES", "meta:provider": ["geoplanet:7.3.1", "geoplanet:7.3.2", "geoplanet:7.4.0", "geoplanet:7.4.1", "geoplanet:7.5.1", "geoplanet:7.5.2", "geoplanet:7.6.0", "geoplanet:7.8.1", "geoplanet:7.9.0", "geoplanet:7.10.0", "geoplanet:8.0.0", "woeplanet:8.0.0"], "meta:indexed": "2020-08-20T20:56:19.654118", "woe:alias_UNK_V": ["Estaci\u00f3n l'eliana", "Estaci\u00f3n del l'eliana"], "woe:alias_UNK_S": ["Estacion de L'eliana", "Estacion del l'eliana", "Estacion l'eliana"], "meta:updated": "2020-10-14T11:28:15.769906", "woe:hierarchy": {"continent": 24865675, "country": 23424950, "town": 0, "planet": 1, "county": 12602139, "suburb": 0, "state": 12578038, "region": 0, "localadmin": 12695653}, "woe:timezone_id": 56043644, "woe:hash": "ezp95f17q6ey", "woe:centroid": [-0.53634, 39.56234], "geom:latitude": 39.56234, "geom:longitude": -0.53634, "geom:hash": "ezp95f17q6ey", "woe:latitude": 39.56234, "geom:centroid": [-0.53634, 39.56234], "woe:longitude": -0.53634, "woe:repo": "woeplanet-poi-es", "geom:area": 0.0, "woe:scale": 19}}