{"type": "Feature", "id": 22414836, "geometry": {"type": "Point", "coordinates": [-3.68427, 40.35297]}, "properties": {"woe:id": 22414836, "woe:parent_id": 778661, "woe:name": "Estaci\u00f3n de Villaverde Bajo", "woe:placetype": 20, "woe:placetype_name": "POI", "woe:lang": "SPA", "iso:country": "ES", "meta:provider": ["geoplanet:7.3.1", "geoplanet:7.3.2", "geoplanet:7.4.0", "geoplanet:7.4.1", "geoplanet:7.5.1", "geoplanet:7.5.2", "geoplanet:7.6.0", "geoplanet:7.8.1", "geoplanet:7.9.0", "geoplanet:7.10.0", "geoplanet:8.0.0", "woeplanet:8.0.0"], "meta:indexed": "2020-08-20T20:56:18.557266", "meta:updated": "2020-10-14T11:28:19.361619", "woe:alias_SPA_S": ["Estacion de Villaverde Bajo", "Estacion del Villaverde Bajo", "Estacion Villaverde Bajo"], "woe:alias_SPA_V": ["Estaci\u00f3n Villaverde Bajo", "Estaci\u00f3n del Villaverde Bajo"], "woe:hierarchy": {"continent": 24865675, "country": 23424950, "town": 0, "planet": 1, "county": 12602090, "suburb": 0, "state": 12578024, "region": 0, "localadmin": 12688024}, "woe:timezone_id": 56043644, "woe:hash": "ezjms4j1n6c4", "woe:centroid": [-3.68427, 40.35297], "geom:latitude": 40.35297, "geom:longitude": -3.68427, "geom:hash": "ezjms4j1n6c4", "woe:latitude": 40.35297, "geom:centroid": [-3.68427, 40.35297], "woe:longitude": -3.68427, "woe:repo": "woeplanet-poi-es", "geom:area": 0.0, "woe:scale": 19}}