{"type": "Feature", "id": 56060774, "properties": {"woe:id": 56060774, "woe:parent_id": 775246, "woe:name": "Universitat Rovira I Virgili", "woe:placetype": 20, "woe:placetype_name": "POI", "woe:lang": "UNK", "iso:country": "ES", "meta:provider": ["geoplanet:7.3.1", "geoplanet:7.3.2", "geoplanet:7.4.0", "geoplanet:7.4.1", "geoplanet:7.5.1", "geoplanet:7.5.2", "geoplanet:7.6.0", "geoplanet:7.8.1", "geoplanet:7.9.0", "geoplanet:7.10.0", "geoplanet:8.0.0", "woeplanet:8.0.0"], "meta:indexed": "2020-08-20T20:56:20.100591", "meta:updated": "2020-08-22T03:00:15.511127", "woe:hierarchy": {"continent": 24865675, "country": 23424950, "town": 0, "planet": 1, "county": 12602127, "suburb": 0, "state": 12578034, "region": 0, "localadmin": 12694288}, "woe:timezone_id": 56043644, "woe:hash": "sp2cuqpy7x9k", "woe:centroid": [1.25225, 41.12294], "geom:latitude": 41.12294, "geom:longitude": 1.25225, "geom:hash": "sp2cuqpy7x9k", "woe:latitude": 41.12294, "geom:centroid": [1.25225, 41.12294], "woe:longitude": 1.25225, "woe:repo": "woeplanet-poi-es"}, "geometry": {"coordinates": [1.25225, 41.12294], "type": "Point"}}