{"type": "Feature", "id": 23268803, "geometry": {"type": "Point", "coordinates": [-0.43862, 42.315071]}, "properties": {"woe:id": 23268803, "woe:parent_id": 752910, "woe:name": "Hospeder\u00eda de Arguis", "woe:placetype": 20, "woe:placetype_name": "POI", "woe:lang": "SPA", "iso:country": "ES", "meta:provider": ["geoplanet:7.3.1", "geoplanet:7.3.2", "geoplanet:7.4.0", "geoplanet:7.4.1", "geoplanet:7.5.1", "geoplanet:7.5.2", "geoplanet:7.6.0", "geoplanet:7.8.1", "geoplanet:7.9.0", "geoplanet:7.10.0", "geoplanet:8.0.0", "woeplanet:8.0.0"], "meta:indexed": "2020-08-20T20:56:19.362698", "meta:updated": "2020-10-14T11:28:15.487571", "woe:alias_SPA_S": ["Hospederia de Arguis"], "woe:hierarchy": {"continent": 24865675, "country": 23424950, "town": 0, "planet": 1, "county": 12602105, "suburb": 0, "state": 12578030, "region": 0, "localadmin": 12689426}, "woe:timezone_id": 56043644, "woe:hash": "ezx8wp0x5kvn", "woe:centroid": [-0.43862, 42.315071], "geom:latitude": 42.315071, "geom:longitude": -0.43862, "geom:hash": "ezx8wp0x5kvn", "woe:latitude": 42.315071, "geom:centroid": [-0.43862, 42.315071], "woe:longitude": -0.43862, "woe:repo": "woeplanet-poi-es", "geom:area": 0.0, "woe:scale": 19}}