{"type": "Feature", "id": 23251760, "properties": {"woe:id": 23251760, "woe:parent_id": 774837, "woe:name": "Centro Cultural Juan Antonio Gaya Nu\u00f1o", "woe:placetype": 20, "woe:placetype_name": "POI", "woe:lang": "SPA", "iso:country": "ES", "meta:provider": ["geoplanet:7.3.1", "geoplanet:7.3.2", "geoplanet:7.4.0", "geoplanet:7.4.1", "geoplanet:7.5.1", "geoplanet:7.5.2", "geoplanet:7.6.0", "geoplanet:7.8.1", "geoplanet:7.9.0", "geoplanet:7.10.0", "geoplanet:8.0.0", "woeplanet:8.0.0"], "meta:indexed": "2020-08-20T20:56:18.977137", "meta:updated": "2020-08-22T03:00:15.098540", "woe:alias_SPA_S": ["Centro Cultural Juan Antonio Gaya Nuno", "Centro Cultural Juan Antonio Gaya Nunyo"], "woe:hierarchy": {"continent": 24865675, "country": 23424950, "town": 0, "planet": 1, "county": 12602121, "suburb": 0, "state": 12578033, "region": 0, "localadmin": 12692863}, "woe:timezone_id": 56043644, "woe:hash": "ezqjxfgebf7b", "woe:centroid": [-2.46708, 41.763809], "geom:latitude": 41.763809, "geom:longitude": -2.46708, "geom:hash": "ezqjxfgebf7b", "woe:latitude": 41.763809, "geom:centroid": [-2.46708, 41.763809], "woe:longitude": -2.46708, "woe:repo": "woeplanet-poi-es"}, "geometry": {"coordinates": [-2.46708, 41.763809], "type": "Point"}}