{"type": "Feature", "id": 23227225, "properties": {"woe:id": 23227225, "woe:parent_id": 20219996, "woe:name": "Estaci\u00f3n de C\u00f3rdoba", "woe:placetype": 20, "woe:placetype_name": "POI", "woe:lang": "SPA", "iso:country": "ES", "meta:provider": ["geoplanet:7.3.1", "geoplanet:7.3.2", "geoplanet:7.4.0", "geoplanet:7.4.1", "geoplanet:7.5.1", "geoplanet:7.5.2", "geoplanet:7.6.0", "geoplanet:7.8.1", "geoplanet:7.9.0", "geoplanet:7.10.0", "geoplanet:8.0.0", "woeplanet:8.0.0"], "meta:indexed": "2020-08-20T20:56:18.660809", "meta:updated": "2020-08-22T03:00:14.983108", "woe:alias_SPA_S": ["Estacion de Cordoba", "Estacion del Cordoba", "Estacion Cordoba"], "woe:alias_SPA_V": ["Estaci\u00f3n de Renfe", "Estacion de Renfe", "Estaci\u00f3n C\u00f3rdoba", "Estaci\u00f3n del C\u00f3rdoba"], "woe:hierarchy": {"continent": 24865675, "country": 23424950, "town": 0, "planet": 1, "county": 12602098, "suburb": 0, "state": 12578029, "region": 0, "localadmin": 12688792}, "woe:timezone_id": 56043644, "woe:hash": "eysxdcrg5049", "woe:centroid": [-4.79025, 37.888241], "geom:latitude": 37.888241, "geom:longitude": -4.79025, "geom:hash": "eysxdcrg5049", "woe:latitude": 37.888241, "geom:centroid": [-4.79025, 37.888241], "woe:longitude": -4.79025, "woe:repo": "woeplanet-poi-es"}, "geometry": {"coordinates": [-4.79025, 37.888241], "type": "Point"}}