{"type": "Feature", "id": 23258214, "properties": {"woe:id": 23258214, "woe:parent_id": 20220084, "woe:name": "Estaci\u00f3n de Sagrada Familia", "woe:placetype": 20, "woe:placetype_name": "POI", "woe:lang": "SPA", "iso:country": "ES", "meta:provider": ["geoplanet:7.3.1", "geoplanet:7.3.2", "geoplanet:7.4.0", "geoplanet:7.4.1", "geoplanet:7.5.1", "geoplanet:7.5.2", "geoplanet:7.6.0", "geoplanet:7.8.1", "geoplanet:7.9.0", "geoplanet:7.10.0", "geoplanet:8.0.0", "woeplanet:8.0.0"], "meta:indexed": "2020-08-20T20:56:19.090946", "woe:alias_UNK_V": ["Metro-Sagrada Familia", "Metro-Sagrada Fam\u00edlia"], "meta:updated": "2020-08-22T03:00:15.141260", "woe:alias_SPA_S": ["Estacion de Sagrada Familia", "Estacion del Sagrada Familia", "Estacion Sagrada Familia"], "woe:alias_SPA_V": ["Estaci\u00f3n Sagrada Familia", "Estaci\u00f3n del Sagrada Familia"], "woe:hierarchy": {"continent": 24865675, "country": 23424950, "town": 0, "planet": 1, "county": 12602124, "suburb": 0, "state": 12578034, "region": 0, "localadmin": 12693396}, "woe:timezone_id": 56043644, "woe:hash": "sp3e93rqg3td", "woe:centroid": [2.17441, 41.404518], "geom:latitude": 41.404518, "geom:longitude": 2.17441, "geom:hash": "sp3e93rqg3td", "woe:latitude": 41.404518, "geom:centroid": [2.17441, 41.404518], "woe:longitude": 2.17441, "woe:repo": "woeplanet-poi-es"}, "geometry": {"coordinates": [2.17441, 41.404518], "type": "Point"}}