{"type": "Feature", "id": 23270372, "properties": {"woe:id": 23270372, "woe:parent_id": 775250, "woe:name": "Mercat Municipal", "woe:placetype": 20, "woe:placetype_name": "POI", "woe:lang": "UNK", "iso:country": "ES", "meta:provider": ["geoplanet:7.3.1", "geoplanet:7.3.2", "geoplanet:7.4.0", "geoplanet:7.4.1", "geoplanet:7.5.1", "geoplanet:7.5.2", "geoplanet:7.6.0", "geoplanet:7.8.1", "geoplanet:7.9.0", "geoplanet:7.10.0", "geoplanet:8.0.0", "woeplanet:8.0.0"], "meta:indexed": "2020-08-20T20:56:19.396122", "meta:updated": "2020-08-22T03:00:15.243722", "woe:hierarchy": {"continent": 24865675, "country": 23424950, "town": 0, "planet": 1, "county": 12602126, "suburb": 0, "state": 12578034, "region": 0, "localadmin": 12694100}, "woe:timezone_id": 56043644, "woe:hash": "sp2ucvqhtyc3", "woe:centroid": [1.14008, 41.645859], "geom:latitude": 41.645859, "geom:longitude": 1.14008, "geom:hash": "sp2ucvqhtyc3", "woe:latitude": 41.645859, "geom:centroid": [1.14008, 41.645859], "woe:longitude": 1.14008, "woe:repo": "woeplanet-poi-es"}, "geometry": {"coordinates": [1.14008, 41.645859], "type": "Point"}}