{"type": "Feature", "id": 23262072, "geometry": {"type": "Point", "coordinates": [1.86894, 41.628471]}, "properties": {"woe:id": 23262072, "woe:parent_id": 20220972, "woe:name": "Estaci\u00f3n de Borr\u00e1s", "woe:placetype": 20, "woe:placetype_name": "POI", "woe:lang": "UNK", "iso:country": "ES", "meta:provider": ["geoplanet:7.3.1", "geoplanet:7.3.2", "geoplanet:7.4.0", "geoplanet:7.4.1", "geoplanet:7.5.1", "geoplanet:7.5.2", "geoplanet:7.6.0", "geoplanet:7.8.1", "geoplanet:7.9.0", "geoplanet:7.10.0", "geoplanet:8.0.0", "woeplanet:8.0.0"], "meta:indexed": "2020-08-20T20:56:19.190716", "woe:alias_UNK_V": ["Estaci\u00f3n Borr\u00e1s", "Estaci\u00f3n del Borr\u00e1s"], "woe:alias_UNK_S": ["Estacion de Borras", "Estacion del Borras", "Estacion Borras"], "meta:updated": "2020-10-14T11:28:15.849515", "woe:hierarchy": {"continent": 24865675, "country": 23424950, "town": 0, "planet": 1, "county": 12602124, "suburb": 0, "state": 12578034, "region": 0, "localadmin": 12693431}, "woe:timezone_id": 56043644, "woe:hash": "sp3kfd0zmmqw", "woe:centroid": [1.86894, 41.628471], "geom:latitude": 41.628471, "geom:longitude": 1.86894, "geom:hash": "sp3kfd0zmmqw", "woe:latitude": 41.628471, "geom:centroid": [1.86894, 41.628471], "woe:longitude": 1.86894, "woe:repo": "woeplanet-poi-es", "geom:area": 0.0, "woe:scale": 19}}