{"type": "Feature", "id": 23249431, "geometry": {"type": "Point", "coordinates": [-5.6677, 40.961571]}, "properties": {"woe:id": 23249431, "woe:parent_id": 772416, "woe:name": "Escuelas Menores", "woe:placetype": 20, "woe:placetype_name": "POI", "woe:lang": "SPA", "iso:country": "ES", "meta:provider": ["geoplanet:7.3.1", "geoplanet:7.3.2", "geoplanet:7.4.0", "geoplanet:7.4.1", "geoplanet:7.5.1", "geoplanet:7.5.2", "geoplanet:7.6.0", "geoplanet:7.8.1", "geoplanet:7.9.0", "geoplanet:7.10.0", "geoplanet:8.0.0", "woeplanet:8.0.0"], "meta:indexed": "2020-08-20T20:56:18.931443", "meta:updated": "2020-10-14T11:28:15.955048", "woe:hierarchy": {"continent": 24865675, "country": 23424950, "town": 0, "planet": 1, "county": 12602119, "suburb": 0, "state": 12578033, "region": 0, "localadmin": 12692406}, "woe:timezone_id": 56043644, "woe:hash": "ez7cp0bfmn28", "woe:centroid": [-5.6677, 40.961571], "geom:latitude": 40.961571, "geom:longitude": -5.6677, "geom:hash": "ez7cp0bfmn28", "woe:latitude": 40.961571, "geom:centroid": [-5.6677, 40.961571], "woe:longitude": -5.6677, "woe:repo": "woeplanet-poi-es", "geom:area": 0.0, "woe:scale": 19}}