{"type": "Feature", "id": 23253441, "properties": {"woe:id": 23253441, "woe:parent_id": 754703, "woe:name": "Estaci\u00f3n de Bolueta", "woe:placetype": 20, "woe:placetype_name": "POI", "woe:lang": "SPA", "iso:country": "ES", "meta:provider": ["geoplanet:7.3.1", "geoplanet:7.3.2", "geoplanet:7.4.0", "geoplanet:7.4.1", "geoplanet:7.5.1", "geoplanet:7.5.2", "geoplanet:7.6.0", "geoplanet:7.8.1", "geoplanet:7.9.0", "geoplanet:7.10.0", "geoplanet:8.0.0", "woeplanet:8.0.0"], "meta:indexed": "2020-08-20T20:56:18.995476", "meta:updated": "2020-08-22T03:00:15.105181", "woe:alias_SPA_S": ["Estacion de Bolueta", "Estacion del Bolueta", "Estacion Bolueta"], "woe:alias_SPA_V": ["Estaci\u00f3n Bolueta", "Estaci\u00f3n del Bolueta"], "woe:hierarchy": {"continent": 24865675, "country": 23424950, "town": 0, "planet": 1, "county": 12602136, "suburb": 0, "state": 12578037, "region": 0, "localadmin": 12695182}, "woe:timezone_id": 56043644, "woe:hash": "eztyjbgkyt5d", "woe:centroid": [-2.90663, 43.24715], "geom:latitude": 43.24715, "geom:longitude": -2.90663, "geom:hash": "eztyjbgkyt5d", "woe:latitude": 43.24715, "geom:centroid": [-2.90663, 43.24715], "woe:longitude": -2.90663, "woe:repo": "woeplanet-poi-es"}, "geometry": {"coordinates": [-2.90663, 43.24715], "type": "Point"}}