{"type": "Feature", "id": 23279940, "geometry": {"type": "Point", "coordinates": [-0.81471, 38.543678]}, "properties": {"woe:id": 23279940, "woe:parent_id": 774250, "woe:name": "Estaci\u00f3n de Sax", "woe:placetype": 20, "woe:placetype_name": "POI", "woe:lang": "SPA", "iso:country": "ES", "meta:provider": ["geoplanet:7.3.1", "geoplanet:7.3.2", "geoplanet:7.4.0", "geoplanet:7.4.1", "geoplanet:7.5.1", "geoplanet:7.5.2", "geoplanet:7.6.0", "geoplanet:7.8.1", "geoplanet:7.9.0", "geoplanet:7.10.0", "geoplanet:8.0.0", "woeplanet:8.0.0"], "meta:indexed": "2020-08-20T20:56:19.540719", "meta:updated": "2020-10-14T11:28:16.323261", "woe:alias_SPA_S": ["Estacion de Sax", "Estacion del Sax", "Estacion Sax"], "woe:alias_SPA_V": ["Estaci\u00f3n Sax", "Estaci\u00f3n del Sax"], "woe:hierarchy": {"continent": 24865675, "country": 23424950, "town": 0, "planet": 1, "county": 12602137, "suburb": 0, "state": 12578038, "region": 0, "localadmin": 12695390}, "woe:timezone_id": 56043644, "woe:hash": "eyz7m2wtpyk5", "woe:centroid": [-0.81471, 38.543678], "geom:latitude": 38.543678, "geom:longitude": -0.81471, "geom:hash": "eyz7m2wtpyk5", "woe:latitude": 38.543678, "geom:centroid": [-0.81471, 38.543678], "woe:longitude": -0.81471, "woe:repo": "woeplanet-poi-es", "geom:area": 0.0, "woe:scale": 19}}