{"type": "Feature", "id": 23237717, "geometry": {"type": "Point", "coordinates": [-2.55999, 42.85387]}, "properties": {"woe:id": 23237717, "woe:parent_id": 768877, "woe:name": "Estaci\u00f3n de Oreitia", "woe:placetype": 20, "woe:placetype_name": "POI", "woe:lang": "SPA", "iso:country": "ES", "meta:provider": ["geoplanet:7.3.1", "geoplanet:7.3.2", "geoplanet:7.4.0", "geoplanet:7.4.1", "geoplanet:7.5.1", "geoplanet:7.5.2", "geoplanet:7.6.0", "geoplanet:7.8.1", "geoplanet:7.9.0", "geoplanet:7.10.0", "geoplanet:8.0.0", "woeplanet:8.0.0"], "meta:indexed": "2020-08-20T20:56:18.799824", "meta:updated": "2020-10-14T11:28:16.214896", "woe:alias_SPA_S": ["Estacion de Oreitia", "Estacion del Oreitia", "Estacion Oreitia"], "woe:alias_SPA_V": ["Estaci\u00f3n Oreitia", "Estaci\u00f3n del Oreitia"], "woe:hierarchy": {"continent": 24865675, "country": 23424950, "town": 0, "planet": 1, "county": 12602134, "suburb": 0, "state": 12578037, "region": 0, "localadmin": 24548829}, "woe:timezone_id": 56043644, "woe:hash": "ezw5v9rcgum5", "woe:centroid": [-2.55999, 42.85387], "geom:latitude": 42.85387, "geom:longitude": -2.55999, "geom:hash": "ezw5v9rcgum5", "woe:latitude": 42.85387, "geom:centroid": [-2.55999, 42.85387], "woe:longitude": -2.55999, "woe:repo": "woeplanet-poi-es", "geom:area": 0.0, "woe:scale": 19}}