{"type": "Feature", "id": 23293301, "properties": {"woe:id": 23293301, "woe:parent_id": 776740, "woe:name": "Estaci\u00f3n de Vallada", "woe:placetype": 20, "woe:placetype_name": "POI", "woe:lang": "SPA", "iso:country": "ES", "meta:provider": ["geoplanet:7.3.1", "geoplanet:7.3.2", "geoplanet:7.4.0", "geoplanet:7.4.1", "geoplanet:7.5.1", "geoplanet:7.5.2", "geoplanet:7.6.0", "geoplanet:7.8.1", "geoplanet:7.9.0", "geoplanet:7.10.0", "geoplanet:8.0.0", "woeplanet:8.0.0"], "meta:indexed": "2020-08-20T20:56:19.749697", "meta:updated": "2020-08-22T03:00:15.381293", "woe:alias_SPA_S": ["Estacion de Vallada", "Estacion del Vallada", "Estacion Vallada"], "woe:alias_SPA_V": ["Estaci\u00f3n Vallada", "Estaci\u00f3n del Vallada"], "woe:hierarchy": {"continent": 24865675, "country": 23424950, "town": 0, "planet": 1, "county": 12602139, "suburb": 0, "state": 12578038, "region": 0, "localadmin": 12695790}, "woe:timezone_id": 56043644, "woe:hash": "eyzt27zumern", "woe:centroid": [-0.68125, 38.912949], "geom:latitude": 38.912949, "geom:longitude": -0.68125, "geom:hash": "eyzt27zumern", "woe:latitude": 38.912949, "geom:centroid": [-0.68125, 38.912949], "woe:longitude": -0.68125, "woe:repo": "woeplanet-poi-es"}, "geometry": {"coordinates": [-0.68125, 38.912949], "type": "Point"}}