{"type": "Feature", "id": 23256715, "properties": {"woe:id": 23256715, "woe:parent_id": 774977, "woe:name": "Estaci\u00f3n de la Bonanova", "woe:placetype": 20, "woe:placetype_name": "POI", "woe:lang": "UNK", "iso:country": "ES", "meta:provider": ["geoplanet:7.3.1", "geoplanet:7.3.2", "geoplanet:7.4.0", "geoplanet:7.4.1", "geoplanet:7.5.1", "geoplanet:7.5.2", "geoplanet:7.6.0", "geoplanet:7.8.1", "geoplanet:7.9.0", "geoplanet:7.10.0", "geoplanet:8.0.0", "woeplanet:8.0.0"], "meta:indexed": "2020-08-20T20:56:19.059497", "woe:alias_UNK_V": ["Estaci\u00f3n la Bonanova", "Estaci\u00f3n del la Bonanova"], "woe:alias_UNK_S": ["Estacion de la Bonanova", "Estacion del la Bonanova", "Estacion la Bonanova"], "meta:updated": "2020-08-22T03:00:15.128656", "woe:hierarchy": {"continent": 24865675, "country": 23424950, "town": 0, "planet": 1, "county": 12602124, "suburb": 0, "state": 12578034, "region": 0, "localadmin": 12693396}, "woe:timezone_id": 56043644, "woe:hash": "sp3e8870ptxu", "woe:centroid": [2.1358, 41.397888], "geom:latitude": 41.397888, "geom:longitude": 2.1358, "geom:hash": "sp3e8870ptxu", "woe:latitude": 41.397888, "geom:centroid": [2.1358, 41.397888], "woe:longitude": 2.1358, "woe:repo": "woeplanet-poi-es"}, "geometry": {"coordinates": [2.1358, 41.397888], "type": "Point"}}